hdl/verilog/shift_reg/src/shift_reg.v
module shift_reg
#(parameter LENGTH = 8)
    (
        input i_clk,
        input i_rst,
        input i_din,
        output o_dout
    );

    reg [LENGTH-1:0] shift_reg;
    assign o_dout = shift_reg[LENGTH-1];

    always @(posedge i_clk) begin
        if (i_rst) begin
            shift_reg = { (LENGTH-1){1'b0} };
        end else begin
            shift_reg = { shift_reg[LENGTH-2:0], i_din };
        end
    end

endmodule

hdl/verilog/shift_reg/src/top_level.v
module top_level
#(parameter LENGTH = 8)
    (
        input wire i_clk,
        input wire i_rst,
        input wire i_din,
        output wire o_dout
    );

    shift_reg #(.LENGTH(LENGTH)) shift_reg_0 (
        .i_clk(i_clk),
        .i_rst(i_rst),
        .i_din(i_din),
        .o_dout(o_dout)
    );

endmodule

hdl/verilog/shift_reg/verif/tb_shift_reg.sv

module tb_shift_reg;

    localparam LENGTH = 8;
    int num_errors = 0;
    reg tb_clk;
    reg tb_rst;
    reg tb_din;
    reg [LENGTH-1:0] tb_word;
    wire tb_dout;

    // instantiation unit under test 
    top_level #(.LENGTH(LENGTH)) dut (
        .i_clk(tb_clk),
        .i_rst(tb_rst),
        .i_din(tb_din),
        .o_dout(tb_dout)
    );

    always #5 tb_clk = ~tb_clk;

    initial begin
        $dumpfile("waveform.vcd");
        $dumpvars;

        num_errors = 0;
        tb_clk = 1;
        tb_rst = 1;
        tb_word = $urandom();
        #10;

        tb_rst = 0;
        for (int i = 0; i < LENGTH; i++) begin
            tb_din = tb_word[i];
            #10;
        end

        $finish;
    end // initial
endmodule

hdl/verilog/shift_reg/sim/waveform.vcd
$date
   Wed Oct 23 15:32:53 2024
$end

$version
  2023.2.2
  $dumpfile ("waveform.vcd") 
$end

$timescale
  1ps
$end

$scope module tb_shift_reg $end
$var reg 32 ! num_errors [31:0] $end
$var reg 1 " tb_clk $end
$var reg 1 # tb_rst $end
$var reg 1 $ tb_din $end
$var reg 8 % tb_word [7:0] $end
$var wire 1 & tb_dout $end
$scope module dut $end
$var wire 1 ' i_clk $end
$var wire 1 ( i_rst $end
$var wire 1 ) i_din $end
$var wire 1 & o_dout $end
$var reg 8 * shift_reg [7:0] $end
$upscope $end
$scope begin Block33_3 $end
$var reg 32 + i [31:0] $end
$upscope $end
$upscope $end
$enddefinitions $end

#0
$dumpvars
b0 !
1"
1#
x$
b11011011 %
0&
1'
1(
x)
b0 *
b0 +
$end

#5000
0"
0'

#10000
1"
0#
1$
1'
0(
1)
b1 *

#15000
0"
0'

#20000
1"
1'
b11 *
b1 +

#25000
0"
0'

#30000
1"
0$
1'
0)
b110 *
b10 +

#35000
0"
0'

#40000
1"
1$
1'
1)
b1101 *
b11 +

#45000
0"
0'

#50000
1"
1'
b11011 *
b100 +

#55000
0"
0'

#60000
1"
0$
1'
0)
b110110 *
b101 +

#65000
0"
0'

#70000
1"
1$
1'
1)
b1101101 *
b110 +

#75000
0"
0'

#80000
1"
1&
1'
b11011011 *
b111 +

#85000
0"
0'

#90000
b1000 +
