hdl/verilog/fir_filter/src/serializer.v

module serializer 
#(
    parameter LENGTH = 24
)(
    input wire i_clk,
    input wire i_rst,
    input wire i_en,
    input wire i_din_valid,
    input wire [LENGTH-1:0] iv_din,
    output wire o_dout
);

    reg [LENGTH-1:0] shift_reg;
    assign o_dout = shift_reg[0];

    always @(posedge i_clk) begin
        if (i_rst) begin
            shift_reg <= { (LENGTH){1'b0} };
        end else if (i_en) begin
            if (i_din_valid) begin
                shift_reg <= iv_din;
            end else begin
                shift_reg <= { 1'b0, shift_reg[LENGTH-1:1] };
            end
        end
    end
endmodule

hdl/verilog/fir_filter/verif/tb_serializer.sv


module tb_serializer;

    localparam LENGTH = 24;
    reg tb_clk;
    reg tb_rst;
    reg tb_en;
    reg tb_din_valid;
    reg [LENGTH-1:0] tb_din;
    wire tb_dout;

    reg [LENGTH-1:0] tb_word;
    logic [LENGTH-1:0] serial_word;
    int num_errors = 0;
    logic tb_err;

    // instantiation unit under test 
    serializer
    #(
        .LENGTH(LENGTH)
    ) dut (
        .i_clk(tb_clk),
        .i_rst(tb_rst),
        .i_en(tb_en),
        .i_din_valid(tb_din_valid),
        .iv_din(tb_din),
        .o_dout(tb_dout)
    );


    task assert_and_report(input [LENGTH-1:0] expected, input [LENGTH-1:0] actual);
    begin
        if (actual == expected) begin
            $display("SUCCESS! Expected: %h, Actual: %h", expected, actual);
            tb_err = 1'b0;
        end else begin
            $display("FAILURE! Expected: %h, Actual: %h", expected, actual);
            num_errors = num_errors + 1;
            tb_err = 1'bx;
        end
    end
    endtask // assert_and_report


    task test_word(input [LENGTH-1:0] word);
    begin
        tb_rst = 0;
        tb_en = 1;
        tb_din_valid = 1;
        tb_din = word;

        for (int i = 0; i < LENGTH; i++) begin
            @(posedge tb_clk);
            tb_din_valid = 0;
            serial_word[i] = tb_dout;
        end
        @(posedge tb_clk);
        assert_and_report(word, serial_word);

        tb_en = 0;
        tb_rst = 1; // reset the dut
        @(posedge tb_clk);

    end
    endtask


    always #5 tb_clk = ~tb_clk;
    initial begin
        $dumpfile("waveform.vcd");
        $dumpvars;

        num_errors = 0;
        tb_clk = 1;
        tb_rst = 1;
        tb_en = 0;

        repeat (100) begin
            tb_word = $urandom();
            $display("Word: %h = %b", tb_word, tb_word);
            test_word(tb_word);
            $display();
        end

        $display();
        $display("Total number of errors: %d", num_errors);
        $display();

        $finish;
    end // initial
endmodule

hdl/verilog/fir_filter/sim_functional/waveform.vcd
$date
   Thu Oct 31 20:38:09 2024
$end

$version
  2023.2.2
  $dumpfile ("waveform.vcd") 
$end

$timescale
  1ns
$end

$scope module tb_serializer $end
$var reg 1 ! tb_clk $end
$var reg 1 " tb_rst $end
$var reg 1 # tb_en $end
$var reg 1 $ tb_din_valid $end
$var reg 24 % tb_din [23:0] $end
$var wire 1 & tb_dout $end
$var reg 24 ' tb_word [23:0] $end
$var reg 24 ( serial_word [23:0] $end
$var reg 32 ) num_errors [31:0] $end
$var reg 1 * tb_err $end
$scope module dut $end
$var wire 1 + i_clk $end
$var wire 1 , i_rst $end
$var wire 1 - i_en $end
$var wire 1 . i_din_valid $end
$var wire 24 / iv_din [23:0] $end
$var wire 1 & o_dout $end
$var reg 24 0 shift_reg [23:0] $end
$upscope $end
$scope task assert_and_report $end
$var reg 24 1 expected [23:0] $end
$var reg 24 2 actual [23:0] $end
$upscope $end
$scope task test_word $end
$var reg 24 3 word [23:0] $end
$scope begin Block53_1 $end
$var reg 32 4 i [31:0] $end
$upscope $end
$upscope $end
$upscope $end
$enddefinitions $end

#0
$dumpvars
1!
0"
1#
1$
b110010010011000111011011 %
1&
b110010010011000111011011 '
bx (
b0 )
x*
1+
0,
1-
1.
b110010010011000111011011 /
b110010010011000111011011 0
bx 1
bx 2
b110010010011000111011011 3
b0 4
$end

#50
0!
0+

#100
1!
0$
bx1 (
1+
0.
b11001001001100011101101 0
b1 4

#150
0!
0+

#200
1!
0&
bx11 (
1+
b1100100100110001110110 0
b10 4

#250
0!
0+

#300
1!
1&
bx011 (
1+
b110010010011000111011 0
b11 4

#350
0!
0+

#400
1!
bx1011 (
1+
b11001001001100011101 0
b100 4

#450
0!
0+

#500
1!
0&
bx11011 (
1+
b1100100100110001110 0
b101 4

#550
0!
0+

#600
1!
1&
bx011011 (
1+
b110010010011000111 0
b110 4

#650
0!
0+

#700
1!
bx1011011 (
1+
b11001001001100011 0
b111 4

#750
0!
0+

#800
1!
bx11011011 (
1+
b1100100100110001 0
b1000 4

#850
0!
0+

#900
1!
0&
bx111011011 (
1+
b110010010011000 0
b1001 4

#950
0!
0+

#1000
1!
bx0111011011 (
1+
b11001001001100 0
b1010 4

#1050
0!
0+

#1100
1!
bx00111011011 (
1+
b1100100100110 0
b1011 4

#1150
0!
0+

#1200
1!
1&
bx000111011011 (
1+
b110010010011 0
b1100 4

#1250
0!
0+

#1300
1!
bx1000111011011 (
1+
b11001001001 0
b1101 4

#1350
0!
0+

#1400
1!
0&
bx11000111011011 (
1+
b1100100100 0
b1110 4

#1450
0!
0+

#1500
1!
bx011000111011011 (
1+
b110010010 0
b1111 4

#1550
0!
0+

#1600
1!
1&
bx0011000111011011 (
1+
b11001001 0
b10000 4

#1650
0!
0+

#1700
1!
0&
bx10011000111011011 (
1+
b1100100 0
b10001 4

#1750
0!
0+

#1800
1!
bx010011000111011011 (
1+
b110010 0
b10010 4

#1850
0!
0+

#1900
1!
1&
bx0010011000111011011 (
1+
b11001 0
b10011 4

#1950
0!
0+

#2000
1!
0&
bx10010011000111011011 (
1+
b1100 0
b10100 4

#2050
0!
0+

#2100
1!
bx010010011000111011011 (
1+
b110 0
b10101 4

#2150
0!
0+

#2200
1!
1&
bx0010010011000111011011 (
1+
b11 0
b10110 4

#2250
0!
0+

#2300
1!
bx10010010011000111011011 (
1+
b1 0
b10111 4

#2350
0!
0+

#2400
1!
0&
b110010010011000111011011 (
1+
b0 0
b11000 4

#2450
0!
0+

#2500
1!
1"
0#
0*
1+
1,
0-
b110010010011000111011011 1
b110010010011000111011011 2

#2550
0!
0+

#2600
1!
0"
1#
1$
b101000010010010010111100 %
b101000010010010010111100 '
1+
0,
1-
1.
b101000010010010010111100 /
b101000010010010010111100 0
b101000010010010010111100 3
b0 4

#2650
0!
0+

#2700
1!
0$
b110010010011000111011010 (
1+
0.
b10100001001001001011110 0
b1 4

#2750
0!
0+

#2800
1!
1&
b110010010011000111011000 (
1+
b1010000100100100101111 0
b10 4

#2850
0!
0+

#2900
1!
b110010010011000111011100 (
1+
b101000010010010010111 0
b11 4

#2950
0!
0+

#3000
1!
1+
b10100001001001001011 0
b100 4

#3050
0!
0+

#3100
1!
1+
b1010000100100100101 0
b101 4

#3150
0!
0+

#3200
1!
0&
b110010010011000111111100 (
1+
b101000010010010010 0
b110 4

#3250
0!
0+

#3300
1!
1&
b110010010011000110111100 (
1+
b10100001001001001 0
b111 4

#3350
0!
0+

#3400
1!
0&
1+
b1010000100100100 0
b1000 4

#3450
0!
0+

#3500
1!
b110010010011000010111100 (
1+
b101000010010010 0
b1001 4

#3550
0!
0+

#3600
1!
1&
1+
b10100001001001 0
b1010 4

#3650
0!
0+

#3700
1!
0&
b110010010011010010111100 (
1+
b1010000100100 0
b1011 4

#3750
0!
0+

#3800
1!
1+
b101000010010 0
b1100 4

#3850
0!
0+

#3900
1!
1&
b110010010010010010111100 (
1+
b10100001001 0
b1101 4

#3950
0!
0+

#4000
1!
0&
1+
b1010000100 0
b1110 4

#4050
0!
0+

#4100
1!
1+
b101000010 0
b1111 4

#4150
0!
0+

#4200
1!
1&
1+
b10100001 0
b10000 4

#4250
0!
0+

#4300
1!
0&
1+
b1010000 0
b10001 4

#4350
0!
0+

#4400
1!
1+
b101000 0
b10010 4

#4450
0!
0+

#4500
1!
1+
b10100 0
b10011 4

#4550
0!
0+

#4600
1!
b110000010010010010111100 (
1+
b1010 0
b10100 4

#4650
0!
0+

#4700
1!
1&
1+
b101 0
b10101 4

#4750
0!
0+

#4800
1!
0&
b111000010010010010111100 (
1+
b10 0
b10110 4

#4850
0!
0+

#4900
1!
1&
b101000010010010010111100 (
1+
b1 0
b10111 4

#4950
0!
0+

#5000
1!
0&
1+
b0 0
b11000 4

#5050
0!
0+

#5100
1!
1"
0#
1+
1,
0-
b101000010010010010111100 1
b101000010010010010111100 2

#5150
0!
0+

#5200
1!
0"
1#
1$
b1111101111000011111100 %
b1111101111000011111100 '
1+
0,
1-
1.
b1111101111000011111100 /
b1111101111000011111100 0
b1111101111000011111100 3
b0 4

#5250
0!
0+

#5300
1!
0$
1+
0.
b111110111100001111110 0
b1 4

#5350
0!
0+

#5400
1!
1&
1+
b11111011110000111111 0
b10 4

#5450
0!
0+

#5500
1!
1+
b1111101111000011111 0
b11 4

#5550
0!
0+

#5600
1!
1+
b111110111100001111 0
b100 4

#5650
0!
0+

#5700
1!
1+
b11111011110000111 0
b101 4

#5750
0!
0+

#5800
1!
1+
b1111101111000011 0
b110 4

#5850
0!
0+

#5900
1!
b101000010010010011111100 (
1+
b111110111100001 0
b111 4

#5950
0!
0+

#6000
1!
0&
1+
b11111011110000 0
b1000 4

#6050
0!
0+

#6100
1!
1+
b1111101111000 0
b1001 4

#6150
0!
0+

#6200
1!
1+
b111110111100 0
b1010 4

#6250
0!
0+

#6300
1!
b101000010010000011111100 (
1+
b11111011110 0
b1011 4

#6350
0!
0+

#6400
1!
1&
1+
b1111101111 0
b1100 4

#6450
0!
0+

#6500
1!
b101000010011000011111100 (
1+
b111110111 0
b1101 4

#6550
0!
0+

#6600
1!
1+
b11111011 0
b1110 4

#6650
0!
0+

#6700
1!
b101000010111000011111100 (
1+
b1111101 0
b1111 4

#6750
0!
0+

#6800
1!
0&
b101000011111000011111100 (
1+
b111110 0
b10000 4

#6850
0!
0+

#6900
1!
1&
b101000001111000011111100 (
1+
b11111 0
b10001 4

#6950
0!
0+

#7000
1!
b101000101111000011111100 (
1+
b1111 0
b10010 4

#7050
0!
0+

#7100
1!
b101001101111000011111100 (
1+
b111 0
b10011 4

#7150
0!
0+

#7200
1!
b101011101111000011111100 (
1+
b11 0
b10100 4

#7250
0!
0+

#7300
1!
b101111101111000011111100 (
1+
b1 0
b10101 4

#7350
0!
0+

#7400
1!
0&
1+
b0 0
b10110 4

#7450
0!
0+

#7500
1!
1+
b10111 4

#7550
0!
0+

#7600
1!
b1111101111000011111100 (
1+
b11000 4

#7650
0!
0+

#7700
1!
1"
0#
1+
1,
0-
b1111101111000011111100 1
b1111101111000011111100 2

#7750
0!
0+

#7800
1!
0"
1#
1$
b100011001100101010001110 %
b100011001100101010001110 '
1+
0,
1-
1.
b100011001100101010001110 /
b100011001100101010001110 0
b100011001100101010001110 3
b0 4

#7850
0!
0+

#7900
1!
0$
1&
1+
0.
b10001100110010101000111 0
b1 4

#7950
0!
0+

#8000
1!
b1111101111000011111110 (
1+
b1000110011001010100011 0
b10 4

#8050
0!
0+

#8100
1!
1+
b100011001100101010001 0
b11 4

#8150
0!
0+

#8200
1!
0&
1+
b10001100110010101000 0
b100 4

#8250
0!
0+

#8300
1!
b1111101111000011101110 (
1+
b1000110011001010100 0
b101 4

#8350
0!
0+

#8400
1!
b1111101111000011001110 (
1+
b100011001100101010 0
b110 4

#8450
0!
0+

#8500
1!
1&
b1111101111000010001110 (
1+
b10001100110010101 0
b111 4

#8550
0!
0+

#8600
1!
0&
1+
b1000110011001010 0
b1000 4

#8650
0!
0+

#8700
1!
1&
1+
b100011001100101 0
b1001 4

#8750
0!
0+

#8800
1!
0&
b1111101111001010001110 (
1+
b10001100110010 0
b1010 4

#8850
0!
0+

#8900
1!
1&
1+
b1000110011001 0
b1011 4

#8950
0!
0+

#9000
1!
0&
b1111101111101010001110 (
1+
b100011001100 0
b1100 4

#9050
0!
0+

#9100
1!
b1111101110101010001110 (
1+
b10001100110 0
b1101 4

#9150
0!
0+

#9200
1!
1&
b1111101100101010001110 (
1+
b1000110011 0
b1110 4

#9250
0!
0+

#9300
1!
1+
b100011001 0
b1111 4

#9350
0!
0+

#9400
1!
0&
1+
b10001100 0
b10000 4

#9450
0!
0+

#9500
1!
1+
b1000110 0
b10001 4

#9550
0!
0+

#9600
1!
1&
b1111001100101010001110 (
1+
b100011 0
b10010 4

#9650
0!
0+

#9700
1!
1+
b10001 0
b10011 4

#9750
0!
0+

#9800
1!
0&
1+
b1000 0
b10100 4

#9850
0!
0+

#9900
1!
b1011001100101010001110 (
1+
b100 0
b10101 4

#9950
0!
0+

#10000
1!
b11001100101010001110 (
1+
b10 0
b10110 4

#10050
0!
0+

#10100
1!
1&
1+
b1 0
b10111 4

#10150
0!
0+

#10200
1!
0&
b100011001100101010001110 (
1+
b0 0
b11000 4

#10250
0!
0+

#10300
1!
1"
0#
1+
1,
0-
b100011001100101010001110 1
b100011001100101010001110 2

#10350
0!
0+

#10400
1!
0"
1#
1$
b1111001111010011110000 %
b1111001111010011110000 '
1+
0,
1-
1.
b1111001111010011110000 /
b1111001111010011110000 0
b1111001111010011110000 3
b0 4

#10450
0!
0+

#10500
1!
0$
1+
0.
b111100111101001111000 0
b1 4

#10550
0!
0+

#10600
1!
b100011001100101010001100 (
1+
b11110011110100111100 0
b10 4

#10650
0!
0+

#10700
1!
b100011001100101010001000 (
1+
b1111001111010011110 0
b11 4

#10750
0!
0+

#10800
1!
1&
b100011001100101010000000 (
1+
b111100111101001111 0
b100 4

#10850
0!
0+

#10900
1!
b100011001100101010010000 (
1+
b11110011110100111 0
b101 4

#10950
0!
0+

#11000
1!
b100011001100101010110000 (
1+
b1111001111010011 0
b110 4

#11050
0!
0+

#11100
1!
b100011001100101011110000 (
1+
b111100111101001 0
b111 4

#11150
0!
0+

#11200
1!
0&
1+
b11110011110100 0
b1000 4

#11250
0!
0+

#11300
1!
1+
b1111001111010 0
b1001 4

#11350
0!
0+

#11400
1!
1&
b100011001100100011110000 (
1+
b111100111101 0
b1010 4

#11450
0!
0+

#11500
1!
0&
b100011001100110011110000 (
1+
b11110011110 0
b1011 4

#11550
0!
0+

#11600
1!
1&
b100011001100010011110000 (
1+
b1111001111 0
b1100 4

#11650
0!
0+

#11700
1!
b100011001101010011110000 (
1+
b111100111 0
b1101 4

#11750
0!
0+

#11800
1!
b100011001111010011110000 (
1+
b11110011 0
b1110 4

#11850
0!
0+

#11900
1!
1+
b1111001 0
b1111 4

#11950
0!
0+

#12000
1!
0&
1+
b111100 0
b10000 4

#12050
0!
0+

#12100
1!
1+
b11110 0
b10001 4

#12150
0!
0+

#12200
1!
1&
1+
b1111 0
b10010 4

#12250
0!
0+

#12300
1!
1+
b111 0
b10011 4

#12350
0!
0+

#12400
1!
1+
b11 0
b10100 4

#12450
0!
0+

#12500
1!
b100111001111010011110000 (
1+
b1 0
b10101 4

#12550
0!
0+

#12600
1!
0&
b101111001111010011110000 (
1+
b0 0
b10110 4

#12650
0!
0+

#12700
1!
1+
b10111 4

#12750
0!
0+

#12800
1!
b1111001111010011110000 (
1+
b11000 4

#12850
0!
0+

#12900
1!
1"
0#
1+
1,
0-
b1111001111010011110000 1
b1111001111010011110000 2

#12950
0!
0+

#13000
1!
0"
1#
1$
b11001111011011101 %
1&
b11001111011011101 '
1+
0,
1-
1.
b11001111011011101 /
b11001111011011101 0
b11001111011011101 3
b0 4

#13050
0!
0+

#13100
1!
0$
0&
b1111001111010011110001 (
1+
0.
b1100111101101110 0
b1 4

#13150
0!
0+

#13200
1!
1&
1+
b110011110110111 0
b10 4

#13250
0!
0+

#13300
1!
b1111001111010011110101 (
1+
b11001111011011 0
b11 4

#13350
0!
0+

#13400
1!
b1111001111010011111101 (
1+
b1100111101101 0
b100 4

#13450
0!
0+

#13500
1!
0&
1+
b110011110110 0
b101 4

#13550
0!
0+

#13600
1!
1&
b1111001111010011011101 (
1+
b11001111011 0
b110 4

#13650
0!
0+

#13700
1!
1+
b1100111101 0
b111 4

#13750
0!
0+

#13800
1!
0&
1+
b110011110 0
b1000 4

#13850
0!
0+

#13900
1!
1&
1+
b11001111 0
b1001 4

#13950
0!
0+

#14000
1!
b1111001111011011011101 (
1+
b1100111 0
b1010 4

#14050
0!
0+

#14100
1!
1+
b110011 0
b1011 4

#14150
0!
0+

#14200
1!
b1111001111111011011101 (
1+
b11001 0
b1100 4

#14250
0!
0+

#14300
1!
0&
1+
b1100 0
b1101 4

#14350
0!
0+

#14400
1!
b1111001101111011011101 (
1+
b110 0
b1110 4

#14450
0!
0+

#14500
1!
1&
b1111001001111011011101 (
1+
b11 0
b1111 4

#14550
0!
0+

#14600
1!
1+
b1 0
b10000 4

#14650
0!
0+

#14700
1!
0&
b1111011001111011011101 (
1+
b0 0
b10001 4

#14750
0!
0+

#14800
1!
1+
b10010 4

#14850
0!
0+

#14900
1!
b1110011001111011011101 (
1+
b10011 4

#14950
0!
0+

#15000
1!
b1100011001111011011101 (
1+
b10100 4

#15050
0!
0+

#15100
1!
b1000011001111011011101 (
1+
b10101 4

#15150
0!
0+

#15200
1!
b11001111011011101 (
1+
b10110 4

#15250
0!
0+

#15300
1!
1+
b10111 4

#15350
0!
0+

#15400
1!
1+
b11000 4

#15450
0!
0+

#15500
1!
1"
0#
1+
1,
0-
b11001111011011101 1
b11001111011011101 2

#15550
0!
0+

#15600
1!
0"
1#
1$
b100110111111111100011110 %
b100110111111111100011110 '
1+
0,
1-
1.
b100110111111111100011110 /
b100110111111111100011110 0
b100110111111111100011110 3
b0 4

#15650
0!
0+

#15700
1!
0$
1&
b11001111011011100 (
1+
0.
b10011011111111110001111 0
b1 4

#15750
0!
0+

#15800
1!
b11001111011011110 (
1+
b1001101111111111000111 0
b10 4

#15850
0!
0+

#15900
1!
1+
b100110111111111100011 0
b11 4

#15950
0!
0+

#16000
1!
1+
b10011011111111110001 0
b100 4

#16050
0!
0+

#16100
1!
0&
1+
b1001101111111111000 0
b101 4

#16150
0!
0+

#16200
1!
1+
b100110111111111100 0
b110 4

#16250
0!
0+

#16300
1!
b11001111010011110 (
1+
b10011011111111110 0
b111 4

#16350
0!
0+

#16400
1!
1&
b11001111000011110 (
1+
b1001101111111111 0
b1000 4

#16450
0!
0+

#16500
1!
b11001111100011110 (
1+
b100110111111111 0
b1001 4

#16550
0!
0+

#16600
1!
1+
b10011011111111 0
b1010 4

#16650
0!
0+

#16700
1!
1+
b1001101111111 0
b1011 4

#16750
0!
0+

#16800
1!
1+
b100110111111 0
b1100 4

#16850
0!
0+

#16900
1!
1+
b10011011111 0
b1101 4

#16950
0!
0+

#17000
1!
b11011111100011110 (
1+
b1001101111 0
b1110 4

#17050
0!
0+

#17100
1!
b11111111100011110 (
1+
b100110111 0
b1111 4

#17150
0!
0+

#17200
1!
1+
b10011011 0
b10000 4

#17250
0!
0+

#17300
1!
1+
b1001101 0
b10001 4

#17350
0!
0+

#17400
1!
0&
b111111111100011110 (
1+
b100110 0
b10010 4

#17450
0!
0+

#17500
1!
1&
1+
b10011 0
b10011 4

#17550
0!
0+

#17600
1!
b10111111111100011110 (
1+
b1001 0
b10100 4

#17650
0!
0+

#17700
1!
0&
b110111111111100011110 (
1+
b100 0
b10101 4

#17750
0!
0+

#17800
1!
1+
b10 0
b10110 4

#17850
0!
0+

#17900
1!
1&
1+
b1 0
b10111 4

#17950
0!
0+

#18000
1!
0&
b100110111111111100011110 (
1+
b0 0
b11000 4

#18050
0!
0+

#18100
1!
1"
0#
1+
1,
0-
b100110111111111100011110 1
b100110111111111100011110 2

#18150
0!
0+

#18200
1!
0"
1#
1$
b1100010011011001011 %
1&
b1100010011011001011 '
1+
0,
1-
1.
b1100010011011001011 /
b1100010011011001011 0
b1100010011011001011 3
b0 4

#18250
0!
0+

#18300
1!
0$
b100110111111111100011111 (
1+
0.
b110001001101100101 0
b1 4

#18350
0!
0+

#18400
1!
0&
1+
b11000100110110010 0
b10 4

#18450
0!
0+

#18500
1!
1&
b100110111111111100011011 (
1+
b1100010011011001 0
b11 4

#18550
0!
0+

#18600
1!
0&
1+
b110001001101100 0
b100 4

#18650
0!
0+

#18700
1!
b100110111111111100001011 (
1+
b11000100110110 0
b101 4

#18750
0!
0+

#18800
1!
1&
1+
b1100010011011 0
b110 4

#18850
0!
0+

#18900
1!
b100110111111111101001011 (
1+
b110001001101 0
b111 4

#18950
0!
0+

#19000
1!
0&
b100110111111111111001011 (
1+
b11000100110 0
b1000 4

#19050
0!
0+

#19100
1!
1&
b100110111111111011001011 (
1+
b1100010011 0
b1001 4

#19150
0!
0+

#19200
1!
1+
b110001001 0
b1010 4

#19250
0!
0+

#19300
1!
0&
1+
b11000100 0
b1011 4

#19350
0!
0+

#19400
1!
b100110111111011011001011 (
1+
b1100010 0
b1100 4

#19450
0!
0+

#19500
1!
1&
b100110111110011011001011 (
1+
b110001 0
b1101 4

#19550
0!
0+

#19600
1!
0&
1+
b11000 0
b1110 4

#19650
0!
0+

#19700
1!
b100110111010011011001011 (
1+
b1100 0
b1111 4

#19750
0!
0+

#19800
1!
b100110110010011011001011 (
1+
b110 0
b10000 4

#19850
0!
0+

#19900
1!
1&
b100110100010011011001011 (
1+
b11 0
b10001 4

#19950
0!
0+

#20000
1!
1+
b1 0
b10010 4

#20050
0!
0+

#20100
1!
0&
b100111100010011011001011 (
1+
b0 0
b10011 4

#20150
0!
0+

#20200
1!
b100101100010011011001011 (
1+
b10100 4

#20250
0!
0+

#20300
1!
b100001100010011011001011 (
1+
b10101 4

#20350
0!
0+

#20400
1!
1+
b10110 4

#20450
0!
0+

#20500
1!
1+
b10111 4

#20550
0!
0+

#20600
1!
b1100010011011001011 (
1+
b11000 4

#20650
0!
0+

#20700
1!
1"
0#
1+
1,
0-
b1100010011011001011 1
b1100010011011001011 2

#20750
0!
0+

#20800
1!
0"
1#
1$
b101000101100001110011001 %
1&
b101000101100001110011001 '
1+
0,
1-
1.
b101000101100001110011001 /
b101000101100001110011001 0
b101000101100001110011001 3
b0 4

#20850
0!
0+

#20900
1!
0$
0&
1+
0.
b10100010110000111001100 0
b1 4

#20950
0!
0+

#21000
1!
b1100010011011001001 (
1+
b1010001011000011100110 0
b10 4

#21050
0!
0+

#21100
1!
1&
1+
b101000101100001110011 0
b11 4

#21150
0!
0+

#21200
1!
1+
b10100010110000111001 0
b100 4

#21250
0!
0+

#21300
1!
0&
b1100010011011011001 (
1+
b1010001011000011100 0
b101 4

#21350
0!
0+

#21400
1!
1+
b101000101100001110 0
b110 4

#21450
0!
0+

#21500
1!
1&
b1100010011010011001 (
1+
b10100010110000111 0
b111 4

#21550
0!
0+

#21600
1!
1+
b1010001011000011 0
b1000 4

#21650
0!
0+

#21700
1!
b1100010011110011001 (
1+
b101000101100001 0
b1001 4

#21750
0!
0+

#21800
1!
0&
1+
b10100010110000 0
b1010 4

#21850
0!
0+

#21900
1!
b1100010001110011001 (
1+
b1010001011000 0
b1011 4

#21950
0!
0+

#22000
1!
1+
b101000101100 0
b1100 4

#22050
0!
0+

#22100
1!
1+
b10100010110 0
b1101 4

#22150
0!
0+

#22200
1!
1&
b1100000001110011001 (
1+
b1010001011 0
b1110 4

#22250
0!
0+

#22300
1!
b1100100001110011001 (
1+
b101000101 0
b1111 4

#22350
0!
0+

#22400
1!
0&
b1101100001110011001 (
1+
b10100010 0
b10000 4

#22450
0!
0+

#22500
1!
1&
1+
b1010001 0
b10001 4

#22550
0!
0+

#22600
1!
0&
1+
b101000 0
b10010 4

#22650
0!
0+

#22700
1!
b101100001110011001 (
1+
b10100 0
b10011 4

#22750
0!
0+

#22800
1!
1+
b1010 0
b10100 4

#22850
0!
0+

#22900
1!
1&
1+
b101 0
b10101 4

#22950
0!
0+

#23000
1!
0&
b1000101100001110011001 (
1+
b10 0
b10110 4

#23050
0!
0+

#23100
1!
1&
1+
b1 0
b10111 4

#23150
0!
0+

#23200
1!
0&
b101000101100001110011001 (
1+
b0 0
b11000 4

#23250
0!
0+

#23300
1!
1"
0#
1+
1,
0-
b101000101100001110011001 1
b101000101100001110011001 2

#23350
0!
0+

#23400
1!
0"
1#
1$
b110110101111000000011011 %
1&
b110110101111000000011011 '
1+
0,
1-
1.
b110110101111000000011011 /
b110110101111000000011011 0
b110110101111000000011011 3
b0 4

#23450
0!
0+

#23500
1!
0$
1+
0.
b11011010111100000001101 0
b1 4

#23550
0!
0+

#23600
1!
0&
b101000101100001110011011 (
1+
b1101101011110000000110 0
b10 4

#23650
0!
0+

#23700
1!
1&
1+
b110110101111000000011 0
b11 4

#23750
0!
0+

#23800
1!
1+
b11011010111100000001 0
b100 4

#23850
0!
0+

#23900
1!
0&
1+
b1101101011110000000 0
b101 4

#23950
0!
0+

#24000
1!
1+
b110110101111000000 0
b110 4

#24050
0!
0+

#24100
1!
1+
b11011010111100000 0
b111 4

#24150
0!
0+

#24200
1!
b101000101100001100011011 (
1+
b1101101011110000 0
b1000 4

#24250
0!
0+

#24300
1!
b101000101100001000011011 (
1+
b110110101111000 0
b1001 4

#24350
0!
0+

#24400
1!
b101000101100000000011011 (
1+
b11011010111100 0
b1010 4

#24450
0!
0+

#24500
1!
1+
b1101101011110 0
b1011 4

#24550
0!
0+

#24600
1!
1&
1+
b110110101111 0
b1100 4

#24650
0!
0+

#24700
1!
b101000101101000000011011 (
1+
b11011010111 0
b1101 4

#24750
0!
0+

#24800
1!
b101000101111000000011011 (
1+
b1101101011 0
b1110 4

#24850
0!
0+

#24900
1!
1+
b110110101 0
b1111 4

#24950
0!
0+

#25000
1!
0&
1+
b11011010 0
b10000 4

#25050
0!
0+

#25100
1!
1&
1+
b1101101 0
b10001 4

#25150
0!
0+

#25200
1!
0&
1+
b110110 0
b10010 4

#25250
0!
0+

#25300
1!
1&
1+
b11011 0
b10011 4

#25350
0!
0+

#25400
1!
b101010101111000000011011 (
1+
b1101 0
b10100 4

#25450
0!
0+

#25500
1!
0&
b101110101111000000011011 (
1+
b110 0
b10101 4

#25550
0!
0+

#25600
1!
1&
b100110101111000000011011 (
1+
b11 0
b10110 4

#25650
0!
0+

#25700
1!
b110110101111000000011011 (
1+
b1 0
b10111 4

#25750
0!
0+

#25800
1!
0&
1+
b0 0
b11000 4

#25850
0!
0+

#25900
1!
1"
0#
1+
1,
0-
b110110101111000000011011 1
b110110101111000000011011 2

#25950
0!
0+

#26000
1!
0"
1#
1$
b100100101111000101011001 %
1&
b100100101111000101011001 '
1+
0,
1-
1.
b100100101111000101011001 /
b100100101111000101011001 0
b100100101111000101011001 3
b0 4

#26050
0!
0+

#26100
1!
0$
0&
1+
0.
b10010010111100010101100 0
b1 4

#26150
0!
0+

#26200
1!
b110110101111000000011001 (
1+
b1001001011110001010110 0
b10 4

#26250
0!
0+

#26300
1!
1&
1+
b100100101111000101011 0
b11 4

#26350
0!
0+

#26400
1!
1+
b10010010111100010101 0
b100 4

#26450
0!
0+

#26500
1!
0&
1+
b1001001011110001010 0
b101 4

#26550
0!
0+

#26600
1!
1&
1+
b100100101111000101 0
b110 4

#26650
0!
0+

#26700
1!
0&
b110110101111000001011001 (
1+
b10010010111100010 0
b111 4

#26750
0!
0+

#26800
1!
1&
1+
b1001001011110001 0
b1000 4

#26850
0!
0+

#26900
1!
0&
b110110101111000101011001 (
1+
b100100101111000 0
b1001 4

#26950
0!
0+

#27000
1!
1+
b10010010111100 0
b1010 4

#27050
0!
0+

#27100
1!
1+
b1001001011110 0
b1011 4

#27150
0!
0+

#27200
1!
1&
1+
b100100101111 0
b1100 4

#27250
0!
0+

#27300
1!
1+
b10010010111 0
b1101 4

#27350
0!
0+

#27400
1!
1+
b1001001011 0
b1110 4

#27450
0!
0+

#27500
1!
1+
b100100101 0
b1111 4

#27550
0!
0+

#27600
1!
0&
1+
b10010010 0
b10000 4

#27650
0!
0+

#27700
1!
1&
1+
b1001001 0
b10001 4

#27750
0!
0+

#27800
1!
0&
1+
b100100 0
b10010 4

#27850
0!
0+

#27900
1!
1+
b10010 0
b10011 4

#27950
0!
0+

#28000
1!
1&
b110100101111000101011001 (
1+
b1001 0
b10100 4

#28050
0!
0+

#28100
1!
0&
1+
b100 0
b10101 4

#28150
0!
0+

#28200
1!
1+
b10 0
b10110 4

#28250
0!
0+

#28300
1!
1&
b100100101111000101011001 (
1+
b1 0
b10111 4

#28350
0!
0+

#28400
1!
0&
1+
b0 0
b11000 4

#28450
0!
0+

#28500
1!
1"
0#
1+
1,
0-
b100100101111000101011001 1
b100100101111000101011001 2

#28550
0!
0+

#28600
1!
0"
1#
1$
b110111111011100010001001 %
1&
b110111111011100010001001 '
1+
0,
1-
1.
b110111111011100010001001 /
b110111111011100010001001 0
b110111111011100010001001 3
b0 4

#28650
0!
0+

#28700
1!
0$
0&
1+
0.
b11011111101110001000100 0
b1 4

#28750
0!
0+

#28800
1!
1+
b1101111110111000100010 0
b10 4

#28850
0!
0+

#28900
1!
1&
1+
b110111111011100010001 0
b11 4

#28950
0!
0+

#29000
1!
0&
1+
b11011111101110001000 0
b100 4

#29050
0!
0+

#29100
1!
b100100101111000101001001 (
1+
b1101111110111000100 0
b101 4

#29150
0!
0+

#29200
1!
1+
b110111111011100010 0
b110 4

#29250
0!
0+

#29300
1!
1&
b100100101111000100001001 (
1+
b11011111101110001 0
b111 4

#29350
0!
0+

#29400
1!
0&
b100100101111000110001001 (
1+
b1101111110111000 0
b1000 4

#29450
0!
0+

#29500
1!
b100100101111000010001001 (
1+
b110111111011100 0
b1001 4

#29550
0!
0+

#29600
1!
1+
b11011111101110 0
b1010 4

#29650
0!
0+

#29700
1!
1&
1+
b1101111110111 0
b1011 4

#29750
0!
0+

#29800
1!
b100100101111100010001001 (
1+
b110111111011 0
b1100 4

#29850
0!
0+

#29900
1!
1+
b11011111101 0
b1101 4

#29950
0!
0+

#30000
1!
0&
1+
b1101111110 0
b1110 4

#30050
0!
0+

