hdl/verilog/fir_filter/src/deserializer.v

module deserializer 
#(
    parameter LENGTH = 24
)(
    input wire i_clk,
    input wire i_rst,
    input wire i_en,
    input wire i_din,
    input wire i_din_valid,
    output reg [LENGTH-1:0] ov_dout,
    output reg o_dout_valid
);

    reg [LENGTH-1:0] shift_reg;

    always @(posedge i_clk) begin
        ov_dout = ov_dout;
        o_dout_valid = o_dout_valid;
        shift_reg = shift_reg;
        if (i_rst) begin
            o_dout_valid = 1'b0;
            shift_reg = { (LENGTH){1'b0} };
            ov_dout = { (LENGTH){1'b0} };
        end else if (i_en) begin
            o_dout_valid = 1'b0;
            shift_reg = { i_din, shift_reg[LENGTH-1:1] };
            if (i_din_valid) begin 
                ov_dout = shift_reg;
                o_dout_valid = 1'b1;
            end
        end
    end
endmodule

hdl/verilog/fir_filter/verif/tb_deserializer.sv

module tb_deserializer;

    localparam LENGTH = 24;
    reg tb_clk;
    reg tb_rst;
    reg tb_en;
    reg tb_din_valid;
    reg tb_din;
    wire [LENGTH-1:0] tb_dout;

    reg [LENGTH-1:0] tb_word;
    int num_errors = 0;
    reg tb_err;

    // instantiation unit under test 
    deserializer
    #(
        .LENGTH(LENGTH)
    ) dut (
        .i_clk(tb_clk),
        .i_rst(tb_rst),
        .i_en(tb_en),
        .i_din_valid(tb_din_valid),
        .i_din(tb_din),
        .ov_dout(tb_dout)
    );


    task assert_and_report(input [LENGTH-1:0] expected, input [LENGTH-1:0] actual);
    begin
        if (actual == expected) begin
            $display("SUCCESS! Expected: %h, Actual: %h", expected, actual);
            tb_err = 1'b0;
        end else begin
            $display("FAILURE! Expected: %h, Actual: %h", expected, actual);
            num_errors = num_errors + 1;
            tb_err = 1'bx;
        end
    end
    endtask // assert_and_report


    task test_word(input [LENGTH-1:0] word);
    begin
        tb_en = 1;
        tb_rst = 0;
        // serialize word, LSB first in
        for (int i = 0; i < LENGTH; i++) begin
            tb_din = word[i];
            if (i == LENGTH-1) begin
                tb_din_valid = 1;
            end
            @(posedge tb_clk);
        end
        assert_and_report(word, tb_dout);
        tb_din_valid = 0;
        tb_en = 0;
        // tb_rst = 1; // reset the dut
        // @(posedge tb_clk);
        // tb_rst = 0;
    end
    endtask // test_word


    always #5 tb_clk = ~tb_clk;
    initial begin
        $dumpfile("waveform.vcd");
        $dumpvars;

        num_errors = 0;
        tb_clk = 1;
        tb_rst = 1;
        tb_en = 0;

        repeat (100) begin
            tb_word = $urandom();
            $display("Word: %h = %b", tb_word, tb_word);
            test_word(tb_word);
            $display();
        end

        $display();
        $display("Total number of errors: %d", num_errors);
        $display();

        $finish;
    end // initial
endmodule

hdl/verilog/fir_filter/sim_functional/waveform.vcd
$date
   Mon Nov  4 10:40:40 2024
$end

$version
  2023.2.2
  $dumpfile ("waveform.vcd") 
$end

$timescale
  1ns
$end

$scope module tb_deserializer $end
$var reg 1 ! tb_clk $end
$var reg 1 " tb_rst $end
$var reg 1 # tb_en $end
$var reg 1 $ tb_din_valid $end
$var reg 1 % tb_din $end
$var wire 24 & tb_dout [23:0] $end
$var reg 24 ' tb_word [23:0] $end
$var reg 32 ( num_errors [31:0] $end
$var reg 1 ) tb_err $end
$scope module dut $end
$var wire 1 * i_clk $end
$var wire 1 + i_rst $end
$var wire 1 , i_en $end
$var wire 1 - i_din $end
$var wire 1 . i_din_valid $end
$var reg 24 / ov_dout [23:0] $end
$var reg 1 0 o_dout_valid $end
$var reg 24 1 shift_reg [23:0] $end
$upscope $end
$scope task assert_and_report $end
$var reg 24 2 expected [23:0] $end
$var reg 24 3 actual [23:0] $end
$upscope $end
$scope task test_word $end
$var reg 24 4 word [23:0] $end
$scope begin Block49_1 $end
$var reg 32 5 i [31:0] $end
$upscope $end
$upscope $end
$upscope $end
$enddefinitions $end

#0
$dumpvars
1!
0"
1#
x$
1%
bx &
b110010010011000111011011 '
b0 (
x)
1*
0+
1,
1-
x.
bx /
00
b1xxxxxxxxxxxxxxxxxxxxxxx 1
bx 2
bx 3
b110010010011000111011011 4
b0 5
$end

#50
0!
0*

#100
1!
1*
b11xxxxxxxxxxxxxxxxxxxxxx 1
b1 5

#150
0!
0*

#200
1!
0%
1*
0-
b11xxxxxxxxxxxxxxxxxxxxx 1
b10 5

#250
0!
0*

#300
1!
1%
1*
1-
b1011xxxxxxxxxxxxxxxxxxxx 1
b11 5

#350
0!
0*

#400
1!
1*
b11011xxxxxxxxxxxxxxxxxxx 1
b100 5

#450
0!
0*

#500
1!
0%
1*
0-
b11011xxxxxxxxxxxxxxxxxx 1
b101 5

#550
0!
0*

#600
1!
1%
1*
1-
b1011011xxxxxxxxxxxxxxxxx 1
b110 5

#650
0!
0*

#700
1!
1*
b11011011xxxxxxxxxxxxxxxx 1
b111 5

#750
0!
0*

#800
1!
1*
b111011011xxxxxxxxxxxxxxx 1
b1000 5

#850
0!
0*

#900
1!
0%
1*
0-
b111011011xxxxxxxxxxxxxx 1
b1001 5

#950
0!
0*

#1000
1!
1*
b111011011xxxxxxxxxxxxx 1
b1010 5

#1050
0!
0*

#1100
1!
1*
b111011011xxxxxxxxxxxx 1
b1011 5

#1150
0!
0*

#1200
1!
1%
1*
1-
b1000111011011xxxxxxxxxxx 1
b1100 5

#1250
0!
0*

#1300
1!
1*
b11000111011011xxxxxxxxxx 1
b1101 5

#1350
0!
0*

#1400
1!
0%
1*
0-
b11000111011011xxxxxxxxx 1
b1110 5

#1450
0!
0*

#1500
1!
1*
b11000111011011xxxxxxxx 1
b1111 5

#1550
0!
0*

#1600
1!
1%
1*
1-
b10011000111011011xxxxxxx 1
b10000 5

#1650
0!
0*

#1700
1!
0%
1*
0-
b10011000111011011xxxxxx 1
b10001 5

#1750
0!
0*

#1800
1!
1*
b10011000111011011xxxxx 1
b10010 5

#1850
0!
0*

#1900
1!
1%
1*
1-
b10010011000111011011xxxx 1
b10011 5

#1950
0!
0*

#2000
1!
0%
1*
0-
b10010011000111011011xxx 1
b10100 5

#2050
0!
0*

#2100
1!
1*
b10010011000111011011xx 1
b10101 5

#2150
0!
0*

#2200
1!
1%
1*
1-
b10010010011000111011011x 1
b10110 5

#2250
0!
0*

#2300
1!
1$
b110010010011000111011011 &
1*
1.
b110010010011000111011011 /
10
b110010010011000111011011 1
b10111 5

#2350
0!
0*

#2400
1!
1#
0$
0%
b101000010010010010111100 '
0)
1*
0-
0.
00
b11001001001100011101101 1
b110010010011000111011011 2
b110010010011000111011011 3
b101000010010010010111100 4
b0 5

#2450
0!
0*

#2500
1!
1*
b1100100100110001110110 1
b1 5

#2550
0!
0*

#2600
1!
1%
1*
1-
b100110010010011000111011 1
b10 5

#2650
0!
0*

#2700
1!
1*
b110011001001001100011101 1
b11 5

#2750
0!
0*

#2800
1!
1*
b111001100100100110001110 1
b100 5

#2850
0!
0*

#2900
1!
1*
b111100110010010011000111 1
b101 5

#2950
0!
0*

#3000
1!
0%
1*
0-
b11110011001001001100011 1
b110 5

#3050
0!
0*

#3100
1!
1%
1*
1-
b101111001100100100110001 1
b111 5

#3150
0!
0*

#3200
1!
0%
1*
0-
b10111100110010010011000 1
b1000 5

#3250
0!
0*

#3300
1!
1*
b1011110011001001001100 1
b1001 5

#3350
0!
0*

#3400
1!
1%
1*
1-
b100101111001100100100110 1
b1010 5

#3450
0!
0*

#3500
1!
0%
1*
0-
b10010111100110010010011 1
b1011 5

#3550
0!
0*

#3600
1!
1*
b1001011110011001001001 1
b1100 5

#3650
0!
0*

#3700
1!
1%
1*
1-
b100100101111001100100100 1
b1101 5

#3750
0!
0*

#3800
1!
0%
1*
0-
b10010010111100110010010 1
b1110 5

#3850
0!
0*

#3900
1!
1*
b1001001011110011001001 1
b1111 5

#3950
0!
0*

#4000
1!
1%
1*
1-
b100100100101111001100100 1
b10000 5

#4050
0!
0*

#4100
1!
0%
1*
0-
b10010010010111100110010 1
b10001 5

#4150
0!
0*

#4200
1!
1*
b1001001001011110011001 1
b10010 5

#4250
0!
0*

#4300
1!
1*
b100100100101111001100 1
b10011 5

#4350
0!
0*

#4400
1!
1*
b10010010010111100110 1
b10100 5

#4450
0!
0*

#4500
1!
1%
1*
1-
b100001001001001011110011 1
b10101 5

#4550
0!
0*

#4600
1!
0%
1*
0-
b10000100100100101111001 1
b10110 5

#4650
0!
0*

#4700
1!
1$
1%
b101000010010010010111100 &
1*
1-
1.
b101000010010010010111100 /
10
b101000010010010010111100 1
b10111 5

#4750
0!
0*

#4800
1!
1#
0$
0%
b1111101111000011111100 '
1*
0-
0.
00
b10100001001001001011110 1
b101000010010010010111100 2
b101000010010010010111100 3
b1111101111000011111100 4
b0 5

#4850
0!
0*

#4900
1!
1*
b1010000100100100101111 1
b1 5

#4950
0!
0*

#5000
1!
1%
1*
1-
b100101000010010010010111 1
b10 5

#5050
0!
0*

#5100
1!
1*
b110010100001001001001011 1
b11 5

#5150
0!
0*

#5200
1!
1*
b111001010000100100100101 1
b100 5

#5250
0!
0*

#5300
1!
1*
b111100101000010010010010 1
b101 5

#5350
0!
0*

#5400
1!
1*
b111110010100001001001001 1
b110 5

#5450
0!
0*

#5500
1!
1*
b111111001010000100100100 1
b111 5

#5550
0!
0*

#5600
1!
0%
1*
0-
b11111100101000010010010 1
b1000 5

#5650
0!
0*

#5700
1!
1*
b1111110010100001001001 1
b1001 5

#5750
0!
0*

#5800
1!
1*
b111111001010000100100 1
b1010 5

#5850
0!
0*

#5900
1!
1*
b11111100101000010010 1
b1011 5

#5950
0!
0*

#6000
1!
1%
1*
1-
b100001111110010100001001 1
b1100 5

#6050
0!
0*

#6100
1!
1*
b110000111111001010000100 1
b1101 5

#6150
0!
0*

#6200
1!
1*
b111000011111100101000010 1
b1110 5

#6250
0!
0*

#6300
1!
1*
b111100001111110010100001 1
b1111 5

#6350
0!
0*

#6400
1!
0%
1*
0-
b11110000111111001010000 1
b10000 5

#6450
0!
0*

#6500
1!
1%
1*
1-
b101111000011111100101000 1
b10001 5

#6550
0!
0*

#6600
1!
1*
b110111100001111110010100 1
b10010 5

#6650
0!
0*

#6700
1!
1*
b111011110000111111001010 1
b10011 5

#6750
0!
0*

#6800
1!
1*
b111101111000011111100101 1
b10100 5

#6850
0!
0*

#6900
1!
1*
b111110111100001111110010 1
b10101 5

#6950
0!
0*

#7000
1!
0%
1*
0-
b11111011110000111111001 1
b10110 5

#7050
0!
0*

#7100
1!
1$
b1111101111000011111100 &
1*
1.
b1111101111000011111100 /
10
b1111101111000011111100 1
b10111 5

#7150
0!
0*

#7200
1!
1#
0$
b100011001100101010001110 '
1*
0.
00
b111110111100001111110 1
b1111101111000011111100 2
b1111101111000011111100 3
b100011001100101010001110 4
b0 5

#7250
0!
0*

#7300
1!
1%
1*
1-
b100011111011110000111111 1
b1 5

#7350
0!
0*

#7400
1!
1*
b110001111101111000011111 1
b10 5

#7450
0!
0*

#7500
1!
1*
b111000111110111100001111 1
b11 5

#7550
0!
0*

#7600
1!
0%
1*
0-
b11100011111011110000111 1
b100 5

#7650
0!
0*

#7700
1!
1*
b1110001111101111000011 1
b101 5

#7750
0!
0*

#7800
1!
1*
b111000111110111100001 1
b110 5

#7850
0!
0*

#7900
1!
1%
1*
1-
b100011100011111011110000 1
b111 5

#7950
0!
0*

#8000
1!
0%
1*
0-
b10001110001111101111000 1
b1000 5

#8050
0!
0*

#8100
1!
1%
1*
1-
b101000111000111110111100 1
b1001 5

#8150
0!
0*

#8200
1!
0%
1*
0-
b10100011100011111011110 1
b1010 5

#8250
0!
0*

#8300
1!
1%
1*
1-
b101010001110001111101111 1
b1011 5

#8350
0!
0*

#8400
1!
0%
1*
0-
b10101000111000111110111 1
b1100 5

#8450
0!
0*

#8500
1!
1*
b1010100011100011111011 1
b1101 5

#8550
0!
0*

#8600
1!
1%
1*
1-
b100101010001110001111101 1
b1110 5

#8650
0!
0*

#8700
1!
1*
b110010101000111000111110 1
b1111 5

#8750
0!
0*

#8800
1!
0%
1*
0-
b11001010100011100011111 1
b10000 5

#8850
0!
0*

#8900
1!
1*
b1100101010001110001111 1
b10001 5

#8950
0!
0*

#9000
1!
1%
1*
1-
b100110010101000111000111 1
b10010 5

#9050
0!
0*

#9100
1!
1*
b110011001010100011100011 1
b10011 5

#9150
0!
0*

#9200
1!
0%
1*
0-
b11001100101010001110001 1
b10100 5

#9250
0!
0*

#9300
1!
1*
b1100110010101000111000 1
b10101 5

#9350
0!
0*

#9400
1!
1*
b110011001010100011100 1
b10110 5

#9450
0!
0*

#9500
1!
1$
1%
b100011001100101010001110 &
1*
1-
1.
b100011001100101010001110 /
10
b100011001100101010001110 1
b10111 5

#9550
0!
0*

#9600
1!
1#
0$
0%
b1111001111010011110000 '
1*
0-
0.
00
b10001100110010101000111 1
b100011001100101010001110 2
b100011001100101010001110 3
b1111001111010011110000 4
b0 5

#9650
0!
0*

#9700
1!
1*
b1000110011001010100011 1
b1 5

#9750
0!
0*

#9800
1!
1*
b100011001100101010001 1
b10 5

#9850
0!
0*

#9900
1!
1*
b10001100110010101000 1
b11 5

#9950
0!
0*

#10000
1!
1%
1*
1-
b100001000110011001010100 1
b100 5

#10050
0!
0*

#10100
1!
1*
b110000100011001100101010 1
b101 5

#10150
0!
0*

#10200
1!
1*
b111000010001100110010101 1
b110 5

#10250
0!
0*

#10300
1!
1*
b111100001000110011001010 1
b111 5

#10350
0!
0*

#10400
1!
0%
1*
0-
b11110000100011001100101 1
b1000 5

#10450
0!
0*

#10500
1!
1*
b1111000010001100110010 1
b1001 5

#10550
0!
0*

#10600
1!
1%
1*
1-
b100111100001000110011001 1
b1010 5

#10650
0!
0*

#10700
1!
0%
1*
0-
b10011110000100011001100 1
b1011 5

#10750
0!
0*

#10800
1!
1%
1*
1-
b101001111000010001100110 1
b1100 5

#10850
0!
0*

#10900
1!
1*
b110100111100001000110011 1
b1101 5

#10950
0!
0*

#11000
1!
1*
b111010011110000100011001 1
b1110 5

#11050
0!
0*

#11100
1!
1*
b111101001111000010001100 1
b1111 5

#11150
0!
0*

#11200
1!
0%
1*
0-
b11110100111100001000110 1
b10000 5

#11250
0!
0*

#11300
1!
1*
b1111010011110000100011 1
b10001 5

#11350
0!
0*

#11400
1!
1%
1*
1-
b100111101001111000010001 1
b10010 5

#11450
0!
0*

#11500
1!
1*
b110011110100111100001000 1
b10011 5

#11550
0!
0*

#11600
1!
1*
b111001111010011110000100 1
b10100 5

#11650
0!
0*

#11700
1!
1*
b111100111101001111000010 1
b10101 5

#11750
0!
0*

#11800
1!
0%
1*
0-
b11110011110100111100001 1
b10110 5

#11850
0!
0*

#11900
1!
1$
b1111001111010011110000 &
1*
1.
b1111001111010011110000 /
10
b1111001111010011110000 1
b10111 5

#11950
0!
0*

#12000
1!
1#
0$
1%
b11001111011011101 '
1*
1-
0.
00
b100111100111101001111000 1
b1111001111010011110000 2
b1111001111010011110000 3
b11001111011011101 4
b0 5

#12050
0!
0*

#12100
1!
0%
1*
0-
b10011110011110100111100 1
b1 5

#12150
0!
0*

#12200
1!
1%
1*
1-
b101001111001111010011110 1
b10 5

#12250
0!
0*

#12300
1!
1*
b110100111100111101001111 1
b11 5

#12350
0!
0*

#12400
1!
1*
b111010011110011110100111 1
b100 5

#12450
0!
0*

#12500
1!
0%
1*
0-
b11101001111001111010011 1
b101 5

#12550
0!
0*

#12600
1!
1%
1*
1-
b101110100111100111101001 1
b110 5

#12650
0!
0*

#12700
1!
1*
b110111010011110011110100 1
b111 5

#12750
0!
0*

#12800
1!
0%
1*
0-
b11011101001111001111010 1
b1000 5

#12850
0!
0*

#12900
1!
1%
1*
1-
b101101110100111100111101 1
b1001 5

#12950
0!
0*

#13000
1!
1*
b110110111010011110011110 1
b1010 5

#13050
0!
0*

#13100
1!
1*
b111011011101001111001111 1
b1011 5

#13150
0!
0*

#13200
1!
1*
b111101101110100111100111 1
b1100 5

#13250
0!
0*

#13300
1!
0%
1*
0-
b11110110111010011110011 1
b1101 5

#13350
0!
0*

#13400
1!
1*
b1111011011101001111001 1
b1110 5

#13450
0!
0*

#13500
1!
1%
1*
1-
b100111101101110100111100 1
b1111 5

#13550
0!
0*

#13600
1!
1*
b110011110110111010011110 1
b10000 5

#13650
0!
0*

#13700
1!
0%
1*
0-
b11001111011011101001111 1
b10001 5

#13750
0!
0*

#13800
1!
1*
b1100111101101110100111 1
b10010 5

#13850
0!
0*

#13900
1!
1*
b110011110110111010011 1
b10011 5

#13950
0!
0*

#14000
1!
1*
b11001111011011101001 1
b10100 5

#14050
0!
0*

#14100
1!
1*
b1100111101101110100 1
b10101 5

#14150
0!
0*

#14200
1!
1*
b110011110110111010 1
b10110 5

#14250
0!
0*

#14300
1!
1$
b11001111011011101 &
1*
1.
b11001111011011101 /
10
b11001111011011101 1
b10111 5

#14350
0!
0*

#14400
1!
1#
0$
b100110111111111100011110 '
1*
0.
00
b1100111101101110 1
b11001111011011101 2
b11001111011011101 3
b100110111111111100011110 4
b0 5

#14450
0!
0*

#14500
1!
1%
1*
1-
b100000000110011110110111 1
b1 5

#14550
0!
0*

#14600
1!
1*
b110000000011001111011011 1
b10 5

#14650
0!
0*

#14700
1!
1*
b111000000001100111101101 1
b11 5

#14750
0!
0*

#14800
1!
1*
b111100000000110011110110 1
b100 5

#14850
0!
0*

#14900
1!
0%
1*
0-
b11110000000011001111011 1
b101 5

#14950
0!
0*

#15000
1!
1*
b1111000000001100111101 1
b110 5

#15050
0!
0*

#15100
1!
1*
b111100000000110011110 1
b111 5

#15150
0!
0*

#15200
1!
1%
1*
1-
b100011110000000011001111 1
b1000 5

#15250
0!
0*

#15300
1!
1*
b110001111000000001100111 1
b1001 5

#15350
0!
0*

#15400
1!
1*
b111000111100000000110011 1
b1010 5

#15450
0!
0*

#15500
1!
1*
b111100011110000000011001 1
b1011 5

#15550
0!
0*

#15600
1!
1*
b111110001111000000001100 1
b1100 5

#15650
0!
0*

#15700
1!
1*
b111111000111100000000110 1
b1101 5

#15750
0!
0*

#15800
1!
1*
b111111100011110000000011 1
b1110 5

#15850
0!
0*

#15900
1!
1*
b111111110001111000000001 1
b1111 5

#15950
0!
0*

#16000
1!
1*
b111111111000111100000000 1
b10000 5

#16050
0!
0*

#16100
1!
1*
b111111111100011110000000 1
b10001 5

#16150
0!
0*

#16200
1!
0%
1*
0-
b11111111110001111000000 1
b10010 5

#16250
0!
0*

#16300
1!
1%
1*
1-
b101111111111000111100000 1
b10011 5

#16350
0!
0*

#16400
1!
1*
b110111111111100011110000 1
b10100 5

#16450
0!
0*

#16500
1!
0%
1*
0-
b11011111111110001111000 1
b10101 5

#16550
0!
0*

#16600
1!
1*
b1101111111111000111100 1
b10110 5

#16650
0!
0*

#16700
1!
1$
1%
b100110111111111100011110 &
1*
1-
1.
b100110111111111100011110 /
10
b100110111111111100011110 1
b10111 5

#16750
0!
0*

#16800
1!
1#
0$
b1100010011011001011 '
1*
0.
00
b110011011111111110001111 1
b100110111111111100011110 2
b100110111111111100011110 3
b1100010011011001011 4
b0 5

#16850
0!
0*

#16900
1!
1*
b111001101111111111000111 1
b1 5

#16950
0!
0*

#17000
1!
0%
1*
0-
b11100110111111111100011 1
b10 5

#17050
0!
0*

#17100
1!
1%
1*
1-
b101110011011111111110001 1
b11 5

#17150
0!
0*

#17200
1!
0%
1*
0-
b10111001101111111111000 1
b100 5

#17250
0!
0*

#17300
1!
1*
b1011100110111111111100 1
b101 5

#17350
0!
0*

#17400
1!
1%
1*
1-
b100101110011011111111110 1
b110 5

#17450
0!
0*

#17500
1!
1*
b110010111001101111111111 1
b111 5

#17550
0!
0*

#17600
1!
0%
1*
0-
b11001011100110111111111 1
b1000 5

#17650
0!
0*

#17700
1!
1%
1*
1-
b101100101110011011111111 1
b1001 5

#17750
0!
0*

#17800
1!
1*
b110110010111001101111111 1
b1010 5

#17850
0!
0*

#17900
1!
0%
1*
0-
b11011001011100110111111 1
b1011 5

#17950
0!
0*

#18000
1!
1*
b1101100101110011011111 1
b1100 5

#18050
0!
0*

#18100
1!
1%
1*
1-
b100110110010111001101111 1
b1101 5

#18150
0!
0*

#18200
1!
0%
1*
0-
b10011011001011100110111 1
b1110 5

#18250
0!
0*

#18300
1!
1*
b1001101100101110011011 1
b1111 5

#18350
0!
0*

#18400
1!
1*
b100110110010111001101 1
b10000 5

#18450
0!
0*

#18500
1!
1%
1*
1-
b100010011011001011100110 1
b10001 5

#18550
0!
0*

#18600
1!
1*
b110001001101100101110011 1
b10010 5

#18650
0!
0*

#18700
1!
0%
1*
0-
b11000100110110010111001 1
b10011 5

#18750
0!
0*

#18800
1!
1*
b1100010011011001011100 1
b10100 5

#18850
0!
0*

#18900
1!
1*
b110001001101100101110 1
b10101 5

#18950
0!
0*

#19000
1!
1*
b11000100110110010111 1
b10110 5

#19050
0!
0*

#19100
1!
1$
b1100010011011001011 &
1*
1.
b1100010011011001011 /
10
b1100010011011001011 1
b10111 5

#19150
0!
0*

#19200
1!
1#
0$
1%
b101000101100001110011001 '
1*
1-
0.
00
b100000110001001101100101 1
b1100010011011001011 2
b1100010011011001011 3
b101000101100001110011001 4
b0 5

#19250
0!
0*

#19300
1!
0%
1*
0-
b10000011000100110110010 1
b1 5

#19350
0!
0*

#19400
1!
1*
b1000001100010011011001 1
b10 5

#19450
0!
0*

#19500
1!
1%
1*
1-
b100100000110001001101100 1
b11 5

#19550
0!
0*

#19600
1!
1*
b110010000011000100110110 1
b100 5

#19650
0!
0*

#19700
1!
0%
1*
0-
b11001000001100010011011 1
b101 5

#19750
0!
0*

#19800
1!
1*
b1100100000110001001101 1
b110 5

#19850
0!
0*

#19900
1!
1%
1*
1-
b100110010000011000100110 1
b111 5

#19950
0!
0*

#20000
1!
1*
b110011001000001100010011 1
b1000 5

#20050
0!
0*

#20100
1!
1*
b111001100100000110001001 1
b1001 5

#20150
0!
0*

#20200
1!
0%
1*
0-
b11100110010000011000100 1
b1010 5

#20250
0!
0*

#20300
1!
1*
b1110011001000001100010 1
b1011 5

#20350
0!
0*

#20400
1!
1*
b111001100100000110001 1
b1100 5

#20450
0!
0*

#20500
1!
1*
b11100110010000011000 1
b1101 5

#20550
0!
0*

#20600
1!
1%
1*
1-
b100001110011001000001100 1
b1110 5

#20650
0!
0*

#20700
1!
1*
b110000111001100100000110 1
b1111 5

#20750
0!
0*

#20800
1!
0%
1*
0-
b11000011100110010000011 1
b10000 5

#20850
0!
0*

#20900
1!
1%
1*
1-
b101100001110011001000001 1
b10001 5

#20950
0!
0*

#21000
1!
0%
1*
0-
b10110000111001100100000 1
b10010 5

#21050
0!
0*

#21100
1!
1*
b1011000011100110010000 1
b10011 5

#21150
0!
0*

#21200
1!
1*
b101100001110011001000 1
b10100 5

#21250
0!
0*

#21300
1!
1%
1*
1-
b100010110000111001100100 1
b10101 5

#21350
0!
0*

#21400
1!
0%
1*
0-
b10001011000011100110010 1
b10110 5

#21450
0!
0*

#21500
1!
1$
1%
b101000101100001110011001 &
1*
1-
1.
b101000101100001110011001 /
10
b101000101100001110011001 1
b10111 5

#21550
0!
0*

#21600
1!
1#
0$
b110110101111000000011011 '
1*
0.
00
b110100010110000111001100 1
b101000101100001110011001 2
b101000101100001110011001 3
b110110101111000000011011 4
b0 5

#21650
0!
0*

#21700
1!
1*
b111010001011000011100110 1
b1 5

#21750
0!
0*

#21800
1!
0%
1*
0-
b11101000101100001110011 1
b10 5

#21850
0!
0*

#21900
1!
1%
1*
1-
b101110100010110000111001 1
b11 5

#21950
0!
0*

#22000
1!
1*
b110111010001011000011100 1
b100 5

#22050
0!
0*

#22100
1!
0%
1*
0-
b11011101000101100001110 1
b101 5

#22150
0!
0*

#22200
1!
1*
b1101110100010110000111 1
b110 5

#22250
0!
0*

#22300
1!
1*
b110111010001011000011 1
b111 5

#22350
0!
0*

#22400
1!
1*
b11011101000101100001 1
b1000 5

#22450
0!
0*

#22500
1!
1*
b1101110100010110000 1
b1001 5

#22550
0!
0*

#22600
1!
1*
b110111010001011000 1
b1010 5

#22650
0!
0*

#22700
1!
1*
b11011101000101100 1
b1011 5

#22750
0!
0*

#22800
1!
1%
1*
1-
b100000001101110100010110 1
b1100 5

#22850
0!
0*

#22900
1!
1*
b110000000110111010001011 1
b1101 5

#22950
0!
0*

#23000
1!
1*
b111000000011011101000101 1
b1110 5

#23050
0!
0*

#23100
1!
1*
b111100000001101110100010 1
b1111 5

#23150
0!
0*

#23200
1!
0%
1*
0-
b11110000000110111010001 1
b10000 5

#23250
0!
0*

#23300
1!
1%
1*
1-
b101111000000011011101000 1
b10001 5

#23350
0!
0*

#23400
1!
0%
1*
0-
b10111100000001101110100 1
b10010 5

#23450
0!
0*

#23500
1!
1%
1*
1-
b101011110000000110111010 1
b10011 5

#23550
0!
0*

#23600
1!
1*
b110101111000000011011101 1
b10100 5

#23650
0!
0*

#23700
1!
0%
1*
0-
b11010111100000001101110 1
b10101 5

#23750
0!
0*

#23800
1!
1%
1*
1-
b101101011110000000110111 1
b10110 5

#23850
0!
0*

#23900
1!
1$
b110110101111000000011011 &
1*
1.
b110110101111000000011011 /
10
b110110101111000000011011 1
b10111 5

#23950
0!
0*

#24000
1!
1#
0$
b100100101111000101011001 '
1*
0.
00
b111011010111100000001101 1
b110110101111000000011011 2
b110110101111000000011011 3
b100100101111000101011001 4
b0 5

#24050
0!
0*

#24100
1!
0%
1*
0-
b11101101011110000000110 1
b1 5

#24150
0!
0*

#24200
1!
1*
b1110110101111000000011 1
b10 5

#24250
0!
0*

#24300
1!
1%
1*
1-
b100111011010111100000001 1
b11 5

#24350
0!
0*

#24400
1!
1*
b110011101101011110000000 1
b100 5

#24450
0!
0*

#24500
1!
0%
1*
0-
b11001110110101111000000 1
b101 5

#24550
0!
0*

#24600
1!
1%
1*
1-
b101100111011010111100000 1
b110 5

#24650
0!
0*

#24700
1!
0%
1*
0-
b10110011101101011110000 1
b111 5

#24750
0!
0*

#24800
1!
1%
1*
1-
b101011001110110101111000 1
b1000 5

#24850
0!
0*

#24900
1!
0%
1*
0-
b10101100111011010111100 1
b1001 5

#24950
0!
0*

#25000
1!
1*
b1010110011101101011110 1
b1010 5

#25050
0!
0*

#25100
1!
1*
b101011001110110101111 1
b1011 5

#25150
0!
0*

#25200
1!
1%
1*
1-
b100010101100111011010111 1
b1100 5

#25250
0!
0*

#25300
1!
1*
b110001010110011101101011 1
b1101 5

#25350
0!
0*

#25400
1!
1*
b111000101011001110110101 1
b1110 5

#25450
0!
0*

#25500
1!
1*
b111100010101100111011010 1
b1111 5

#25550
0!
0*

#25600
1!
0%
1*
0-
b11110001010110011101101 1
b10000 5

#25650
0!
0*

#25700
1!
1%
1*
1-
b101111000101011001110110 1
b10001 5

#25750
0!
0*

#25800
1!
0%
1*
0-
b10111100010101100111011 1
b10010 5

#25850
0!
0*

#25900
1!
1*
b1011110001010110011101 1
b10011 5

#25950
0!
0*

#26000
1!
1%
1*
1-
b100101111000101011001110 1
b10100 5

#26050
0!
0*

#26100
1!
0%
1*
0-
b10010111100010101100111 1
b10101 5

#26150
0!
0*

#26200
1!
1*
b1001011110001010110011 1
b10110 5

#26250
0!
0*

#26300
1!
1$
1%
b100100101111000101011001 &
1*
1-
1.
b100100101111000101011001 /
10
b100100101111000101011001 1
b10111 5

#26350
0!
0*

#26400
1!
1#
0$
b110111111011100010001001 '
1*
0.
00
b110010010111100010101100 1
b100100101111000101011001 2
b100100101111000101011001 3
b110111111011100010001001 4
b0 5

#26450
0!
0*

#26500
1!
0%
1*
0-
b11001001011110001010110 1
b1 5

#26550
0!
0*

#26600
1!
1*
b1100100101111000101011 1
b10 5

#26650
0!
0*

#26700
1!
1%
1*
1-
b100110010010111100010101 1
b11 5

#26750
0!
0*

#26800
1!
0%
1*
0-
b10011001001011110001010 1
b100 5

#26850
0!
0*

#26900
1!
1*
b1001100100101111000101 1
b101 5

#26950
0!
0*

#27000
1!
1*
b100110010010111100010 1
b110 5

#27050
0!
0*

#27100
1!
1%
1*
1-
b100010011001001011110001 1
b111 5

#27150
0!
0*

#27200
1!
0%
1*
0-
b10001001100100101111000 1
b1000 5

#27250
0!
0*

#27300
1!
1*
b1000100110010010111100 1
b1001 5

#27350
0!
0*

#27400
1!
1*
b100010011001001011110 1
b1010 5

#27450
0!
0*

#27500
1!
1%
1*
1-
b100010001001100100101111 1
b1011 5

#27550
0!
0*

#27600
1!
1*
b110001000100110010010111 1
b1100 5

#27650
0!
0*

#27700
1!
1*
b111000100010011001001011 1
b1101 5

#27750
0!
0*

#27800
1!
0%
1*
0-
b11100010001001100100101 1
b1110 5

#27850
0!
0*

#27900
1!
1%
1*
1-
b101110001000100110010010 1
b1111 5

#27950
0!
0*

#28000
1!
1*
b110111000100010011001001 1
b10000 5

#28050
0!
0*

#28100
1!
1*
b111011100010001001100100 1
b10001 5

#28150
0!
0*

#28200
1!
1*
b111101110001000100110010 1
b10010 5

#28250
0!
0*

#28300
1!
1*
b111110111000100010011001 1
b10011 5

#28350
0!
0*

#28400
1!
1*
b111111011100010001001100 1
b10100 5

#28450
0!
0*

#28500
1!
0%
1*
0-
b11111101110001000100110 1
b10101 5

#28550
0!
0*

#28600
1!
1%
1*
1-
b101111110111000100010011 1
b10110 5

#28650
0!
0*

#28700
1!
1$
b110111111011100010001001 &
1*
1.
b110111111011100010001001 /
10
b110111111011100010001001 1
b10111 5

#28750
0!
0*

#28800
1!
1#
0$
0%
b110111001000111011111000 '
1*
0-
0.
00
b11011111101110001000100 1
b110111111011100010001001 2
b110111111011100010001001 3
b110111001000111011111000 4
b0 5

#28850
0!
0*

#28900
1!
1*
b1101111110111000100010 1
b1 5

#28950
0!
0*

#29000
1!
1*
b110111111011100010001 1
b10 5

#29050
0!
0*

#29100
1!
1%
1*
1-
b100011011111101110001000 1
b11 5

#29150
0!
0*

