hdl/verilog/fir_filter/src/serializer_fsm.v


module serializer_fsm
#(
    parameter LENGTH = 24
)(
    input wire i_clk,
    input wire i_rst,
    input wire i_en,
    input wire [LENGTH-1:0] iv_din,
    input wire i_din_valid,
    input wire i_ready,
    output reg o_ready,
    output wire o_dout,
    output reg o_dout_valid
);

    reg [LENGTH-1:0] shift_reg;
    assign o_dout = shift_reg[0];

    localparam LENGTH_BITS = $clog2(LENGTH)+1;
    reg [LENGTH_BITS-1:0] counter = { (LENGTH){1'b0} };

    parameter S0 = 4'b0000,
        S1 = 4'b0001,
        S2 = 4'b0010,
        S3 = 4'b0011;
    reg [3:0] state = S0;
    reg [3:0] next_state;


    // STATE REGISTER
    always @(posedge i_clk) begin
        if (i_rst) state <= S0;
        else if (i_en) state <= next_state;
    end

    // STATE MACHINE
    always @(*) begin
        case (state)
            S0: begin
                next_state <= S0;
                // WAIT FOR INPUT DATA VALID
                if (i_din_valid)
                    next_state <= S1;
            end
            S1: begin
                next_state <= S2;
            end
            S2: begin
                next_state <= S2;
                if (i_ready)
                    next_state <= S3;
            end
            S3: begin
                next_state <= S3;
                // DATA SHIFT
                if (counter == LENGTH)
                    next_state <= S0;
            end
            default: next_state <= S0;
        endcase
    end

    // OUTPUT LOGIC
    always @(posedge i_clk) begin
        if (i_rst) begin
            o_ready <= 1'b0;
            o_dout_valid <= 1'b0;
            counter <= 0;
            shift_reg <= 0;
        end else if (i_en) begin
            o_ready <= 1'b0;
            o_dout_valid <= 1'b0;
            counter <= 0;
            shift_reg <= shift_reg;
            case (state)
                S0: begin
                    // WAIT FOR DIN VALID
                    shift_reg <= 0;
                end
                S1: begin
                    // SIGNAL DIN CONSUMED
                    o_ready <= 1'b1;
                    shift_reg <= iv_din;
                end
                S2: begin
                    // SIGNAL DOUT VALID
                    o_dout_valid <= 1'b1;
                end
                S3: begin
                    // DATA SHIFT
                    if (i_ready) begin
                        counter <= counter + 1;
                        o_dout_valid <= 1'b1;
                        shift_reg <= { 1'b0, shift_reg[LENGTH-1:1] };
                    end
                end
                default: begin
                end
            endcase
        end
    end
endmodule

hdl/verilog/fir_filter/verif/tb_serializer.sv


module tb_serializer;

    localparam LENGTH = 24;
    reg tb_clk;
    reg tb_rst;
    reg tb_en;
    reg [LENGTH-1:0] tb_din;
    reg tb_din_valid;
    reg tb_ready;
    wire dut_ready;
    wire tb_dout;
    wire tb_dout_valid;

    reg [LENGTH-1:0] tb_word;
    logic [LENGTH-1:0] serial_word;
    int num_errors = 0;
    logic tb_err;

    // instantiation unit under test 
    serializer_fsm
    #(
        .LENGTH(LENGTH)
    ) dut (
        .i_clk(tb_clk),
        .i_rst(tb_rst),
        .i_en(tb_en),
        .iv_din(tb_din),
        .i_din_valid(tb_din_valid),
        .i_ready(tb_ready),
        .o_ready(dut_ready),
        .o_dout(tb_dout),
        .o_dout_valid(tb_dout_valid)
    );


    task assert_and_report(input [LENGTH-1:0] expected, input [LENGTH-1:0] actual);
    begin
        if (actual == expected) begin
            $display(" SUCCESS!\n  Expected: %b\n  Actual:   %b", expected, actual);
            tb_err = 1'b0;
        end else begin
            $display(" FAILURE!\n  Expected: %b\n  Actual:   %b", expected, actual);
            num_errors = num_errors + 1;
            tb_err = 1'bx;
        end
    end
    endtask // assert_and_report


    task test_word(input [LENGTH-1:0] word);
    begin
        tb_din_valid = 0;
        @(posedge tb_clk);
        tb_en = 1;
        tb_rst = 0;
        tb_din = word;
        tb_din_valid = 1;

        wait (dut_ready == 1'b1);
        @(posedge tb_clk);

        for (int i = 0; i < LENGTH; i++) begin
            serial_word[i] = tb_dout;
            @(posedge tb_clk);
        end

        tb_din_valid = 0;
        wait(tb_dout_valid == 1'b1); // waits for dout valid from dut
        @(posedge tb_clk);
        tb_ready = 1; // consume dout from dut

        assert_and_report(word, serial_word);

        @(posedge tb_clk);
        tb_ready = 0;

        // arbitrary wait
        for (int i = 0; i < 50; i++) begin
            @(posedge tb_clk);
        end

    end
    endtask


    always #5 tb_clk = ~tb_clk;
    initial begin
        $dumpfile("waveform.vcd");
        $dumpvars;

        num_errors = 0;
        tb_clk = 1;
        tb_rst = 1;
        tb_en = 0;

        tb_word = 24'b1111_1111_0000_0000_1111_1111;
        $display("Word: %h = %b", tb_word, tb_word);
        test_word(tb_word);
        $display();

        tb_word = 24'b0000_0000_1111_1111_0000_0000;
        $display("Word: %h = %b", tb_word, tb_word);
        test_word(tb_word);
        $display();

        tb_word = 24'b1010_1111_0101_1110_1011_1001;
        $display("Word: %h = %b", tb_word, tb_word);
        test_word(tb_word);
        $display();


        repeat (100) begin
            tb_word = $urandom();
            $display("Word: %h = %b", tb_word, tb_word);
            test_word(tb_word);
            $display();
        end

        $display();
        $display("Total number of errors: %d", num_errors);
        $display();

        $finish;
    end // initial


    initial begin
        #50ms; // Wait for 1ms simulation time
        $display("Simulation terminated after 50 milliseconds.");
        $finish;
    end // initial
endmodule

hdl/verilog/fir_filter/sim_functional/waveform.vcd
$date
   Tue Nov 12 20:12:15 2024
$end

$version
  2023.2.2
  $dumpfile ("waveform.vcd") 
$end

$timescale
  1ns
$end

$scope module tb_serializer $end
$var reg 1 ! tb_clk $end
$var reg 1 " tb_rst $end
$var reg 1 # tb_en $end
$var reg 24 $ tb_din [23:0] $end
$var reg 1 % tb_din_valid $end
$var reg 1 & tb_ready $end
$var wire 1 ' dut_ready $end
$var wire 1 ( tb_dout $end
$var wire 1 ) tb_dout_valid $end
$var reg 24 * tb_word [23:0] $end
$var reg 24 + serial_word [23:0] $end
$var reg 32 , num_errors [31:0] $end
$var reg 1 - tb_err $end
$scope module dut $end
$var wire 1 . i_clk $end
$var wire 1 / i_rst $end
$var wire 1 0 i_en $end
$var wire 24 1 iv_din [23:0] $end
$var wire 1 2 i_din_valid $end
$var wire 1 3 i_ready $end
$var reg 1 4 o_ready $end
$var wire 1 ( o_dout $end
$var reg 1 5 o_dout_valid $end
$var reg 24 6 shift_reg [23:0] $end
$var reg 5 7 counter [4:0] $end
$var reg 4 8 state [3:0] $end
$var reg 4 9 next_state [3:0] $end
$upscope $end
$scope task assert_and_report $end
$var reg 24 : expected [23:0] $end
$var reg 24 ; actual [23:0] $end
$upscope $end
$scope task test_word $end
$var reg 24 < word [23:0] $end
$scope begin Block64_4 $end
$var reg 32 = i [31:0] $end
$upscope $end
$scope begin Block80_5 $end
$var reg 32 > i [31:0] $end
$upscope $end
$upscope $end
$upscope $end
$enddefinitions $end

#0
$dumpvars
1!
1"
0#
bx $
0%
x&
0'
x(
0)
b111111110000000011111111 *
bx +
b0 ,
x-
1.
1/
00
bx 1
02
x3
04
05
bx 6
b0 7
b1 8
b1 9
bx :
bx ;
b111111110000000011111111 <
b0 =
b0 >
$end

#50
0!
0.

#100
1!
0"
1#
b111111110000000011111111 $
1%
0(
1.
0/
10
b111111110000000011111111 1
12
b0 6
b10 9

#150
0!
0.

#200
1!
1.
b10 8
b100 9

#250
0!
0.

#300
1!
1'
1(
1.
14
b111111110000000011111111 6
b100 8

#350
0!
0.

#400
1!
0'
bx1 +
1.
04
b11111111000000001111111 6
b1 7

#450
0!
0.

#500
1!
bx11 +
1.
b1111111100000000111111 6
b10 7
b1 =

#550
0!
0.

#600
1!
bx111 +
1.
b111111110000000011111 6
b11 7
b10 =

#650
0!
0.

#700
1!
bx1111 +
1.
b11111111000000001111 6
b100 7
b11 =

#750
0!
0.

#800
1!
bx11111 +
1.
b1111111100000000111 6
b101 7
b100 =

#850
0!
0.

#900
1!
bx111111 +
1.
b111111110000000011 6
b110 7
b101 =

#950
0!
0.

#1000
1!
bx1111111 +
1.
b11111111000000001 6
b111 7
b110 =

#1050
0!
0.

#1100
1!
0(
bx11111111 +
1.
b1111111100000000 6
b1000 7
b111 =

#1150
0!
0.

#1200
1!
bx011111111 +
1.
b111111110000000 6
b1001 7
b1000 =

#1250
0!
0.

#1300
1!
bx0011111111 +
1.
b11111111000000 6
b1010 7
b1001 =

#1350
0!
0.

#1400
1!
bx00011111111 +
1.
b1111111100000 6
b1011 7
b1010 =

#1450
0!
0.

#1500
1!
bx000011111111 +
1.
b111111110000 6
b1100 7
b1011 =

#1550
0!
0.

#1600
1!
bx0000011111111 +
1.
b11111111000 6
b1101 7
b1100 =

#1650
0!
0.

#1700
1!
bx00000011111111 +
1.
b1111111100 6
b1110 7
b1101 =

#1750
0!
0.

#1800
1!
bx000000011111111 +
1.
b111111110 6
b1111 7
b1110 =

#1850
0!
0.

#1900
1!
1(
bx0000000011111111 +
1.
b11111111 6
b10000 7
b1111 =

#1950
0!
0.

#2000
1!
bx10000000011111111 +
1.
b1111111 6
b10001 7
b10000 =

#2050
0!
0.

#2100
1!
bx110000000011111111 +
1.
b111111 6
b10010 7
b10001 =

#2150
0!
0.

#2200
1!
bx1110000000011111111 +
1.
b11111 6
b10011 7
b10010 =

#2250
0!
0.

#2300
1!
bx11110000000011111111 +
1.
b1111 6
b10100 7
b10011 =

#2350
0!
0.

#2400
1!
bx111110000000011111111 +
1.
b111 6
b10101 7
b10100 =

#2450
0!
0.

#2500
1!
bx1111110000000011111111 +
1.
b11 6
b10110 7
b10101 =

#2550
0!
0.

#2600
1!
bx11111110000000011111111 +
1.
b1 6
b10111 7
b1000 9
b10110 =

#2650
0!
0.

#2700
1!
b111111110000000011111111 +
1.
b0 7
b1000 8
b10111 =

#2750
0!
0.

#2800
1!
0%
1)
1.
02
15
b11000 =

#2850
0!
0.

#2900
1!
1&
0-
1.
13
b1 9
b111111110000000011111111 :
b111111110000000011111111 ;

#2950
0!
0.

#3000
1!
0&
1.
03
b1 8
b1 9

#3050
0!
0.

#3100
1!
0(
1.
b0 6
b1 >

#3150
0!
0.

#3200
1!
1.
b10 >

#3250
0!
0.

#3300
1!
1.
b11 >

#3350
0!
0.

#3400
1!
1.
b100 >

#3450
0!
0.

#3500
1!
1.
b101 >

#3550
0!
0.

#3600
1!
1.
b110 >

#3650
0!
0.

#3700
1!
1.
b111 >

#3750
0!
0.

#3800
1!
1.
b1000 >

#3850
0!
0.

#3900
1!
1.
b1001 >

#3950
0!
0.

#4000
1!
1.
b1010 >

#4050
0!
0.

#4100
1!
1.
b1011 >

#4150
0!
0.

#4200
1!
1.
b1100 >

#4250
0!
0.

#4300
1!
1.
b1101 >

#4350
0!
0.

#4400
1!
1.
b1110 >

#4450
0!
0.

#4500
1!
1.
b1111 >

#4550
0!
0.

#4600
1!
1.
b10000 >

#4650
0!
0.

#4700
1!
1.
b10001 >

#4750
0!
0.

#4800
1!
1.
b10010 >

#4850
0!
0.

#4900
1!
1.
b10011 >

#4950
0!
0.

#5000
1!
1.
b10100 >

#5050
0!
0.

#5100
1!
1.
b10101 >

#5150
0!
0.

#5200
1!
1.
b10110 >

#5250
0!
0.

#5300
1!
1.
b10111 >

#5350
0!
0.

#5400
1!
1.
b11000 >

#5450
0!
0.

#5500
1!
1.
b11001 >

#5550
0!
0.

#5600
1!
1.
b11010 >

#5650
0!
0.

#5700
1!
1.
b11011 >

#5750
0!
0.

#5800
1!
1.
b11100 >

#5850
0!
0.

#5900
1!
1.
b11101 >

#5950
0!
0.

#6000
1!
1.
b11110 >

#6050
0!
0.

#6100
1!
1.
b11111 >

#6150
0!
0.

#6200
1!
1.
b100000 >

#6250
0!
0.

#6300
1!
1.
b100001 >

#6350
0!
0.

#6400
1!
1.
b100010 >

#6450
0!
0.

#6500
1!
1.
b100011 >

#6550
0!
0.

#6600
1!
1.
b100100 >

#6650
0!
0.

#6700
1!
1.
b100101 >

#6750
0!
0.

#6800
1!
1.
b100110 >

#6850
0!
0.

#6900
1!
1.
b100111 >

#6950
0!
0.

#7000
1!
1.
b101000 >

#7050
0!
0.

#7100
1!
1.
b101001 >

#7150
0!
0.

#7200
1!
1.
b101010 >

#7250
0!
0.

#7300
1!
1.
b101011 >

#7350
0!
0.

#7400
1!
1.
b101100 >

#7450
0!
0.

#7500
1!
1.
b101101 >

#7550
0!
0.

#7600
1!
1.
b101110 >

#7650
0!
0.

#7700
1!
1.
b101111 >

#7750
0!
0.

#7800
1!
1.
b110000 >

#7850
0!
0.

#7900
1!
1.
b110001 >

#7950
0!
0.

#8000
1!
b1111111100000000 *
1.
b1111111100000000 <
b110010 >

#8050
0!
0.

#8100
1!
b1111111100000000 $
1%
1.
b1111111100000000 1
12
b10 9

#8150
0!
0.

#8200
1!
1.
b10 8
b100 9

#8250
0!
0.

#8300
1!
1'
1.
14
b1111111100000000 6
b100 8

#8350
0!
0.

#8400
1!
0'
b111111110000000011111110 +
1.
04
b111111110000000 6
b1 7
b0 =

#8450
0!
0.

#8500
1!
b111111110000000011111100 +
1.
b11111111000000 6
b10 7
b1 =

#8550
0!
0.

#8600
1!
b111111110000000011111000 +
1.
b1111111100000 6
b11 7
b10 =

#8650
0!
0.

#8700
1!
b111111110000000011110000 +
1.
b111111110000 6
b100 7
b11 =

#8750
0!
0.

#8800
1!
b111111110000000011100000 +
1.
b11111111000 6
b101 7
b100 =

#8850
0!
0.

#8900
1!
b111111110000000011000000 +
1.
b1111111100 6
b110 7
b101 =

#8950
0!
0.

#9000
1!
b111111110000000010000000 +
1.
b111111110 6
b111 7
b110 =

#9050
0!
0.

#9100
1!
1(
b111111110000000000000000 +
1.
b11111111 6
b1000 7
b111 =

#9150
0!
0.

#9200
1!
b111111110000000100000000 +
1.
b1111111 6
b1001 7
b1000 =

#9250
0!
0.

#9300
1!
b111111110000001100000000 +
1.
b111111 6
b1010 7
b1001 =

#9350
0!
0.

#9400
1!
b111111110000011100000000 +
1.
b11111 6
b1011 7
b1010 =

#9450
0!
0.

#9500
1!
b111111110000111100000000 +
1.
b1111 6
b1100 7
b1011 =

#9550
0!
0.

#9600
1!
b111111110001111100000000 +
1.
b111 6
b1101 7
b1100 =

#9650
0!
0.

#9700
1!
b111111110011111100000000 +
1.
b11 6
b1110 7
b1101 =

#9750
0!
0.

#9800
1!
b111111110111111100000000 +
1.
b1 6
b1111 7
b1110 =

#9850
0!
0.

#9900
1!
0(
b111111111111111100000000 +
1.
b0 6
b10000 7
b1111 =

#9950
0!
0.

#10000
1!
b111111101111111100000000 +
1.
b10001 7
b10000 =

#10050
0!
0.

#10100
1!
b111111001111111100000000 +
1.
b10010 7
b10001 =

#10150
0!
0.

#10200
1!
b111110001111111100000000 +
1.
b10011 7
b10010 =

#10250
0!
0.

#10300
1!
b111100001111111100000000 +
1.
b10100 7
b10011 =

#10350
0!
0.

#10400
1!
b111000001111111100000000 +
1.
b10101 7
b10100 =

#10450
0!
0.

#10500
1!
b110000001111111100000000 +
1.
b10110 7
b10101 =

#10550
0!
0.

#10600
1!
b100000001111111100000000 +
1.
b10111 7
b1000 9
b10110 =

#10650
0!
0.

#10700
1!
b1111111100000000 +
1.
b0 7
b1000 8
b10111 =

#10750
0!
0.

#10800
1!
0%
1.
02
b11000 =

#10850
0!
0.

#10900
1!
1&
1.
13
b1 9
b1111111100000000 :
b1111111100000000 ;

#10950
0!
0.

#11000
1!
0&
1.
03
b1 8
b1 9
b0 >

#11050
0!
0.

#11100
1!
1.
b1 >

#11150
0!
0.

#11200
1!
1.
b10 >

#11250
0!
0.

#11300
1!
1.
b11 >

#11350
0!
0.

#11400
1!
1.
b100 >

#11450
0!
0.

#11500
1!
1.
b101 >

#11550
0!
0.

#11600
1!
1.
b110 >

#11650
0!
0.

#11700
1!
1.
b111 >

#11750
0!
0.

#11800
1!
1.
b1000 >

#11850
0!
0.

#11900
1!
1.
b1001 >

#11950
0!
0.

#12000
1!
1.
b1010 >

#12050
0!
0.

#12100
1!
1.
b1011 >

#12150
0!
0.

#12200
1!
1.
b1100 >

#12250
0!
0.

#12300
1!
1.
b1101 >

#12350
0!
0.

#12400
1!
1.
b1110 >

#12450
0!
0.

#12500
1!
1.
b1111 >

#12550
0!
0.

#12600
1!
1.
b10000 >

#12650
0!
0.

#12700
1!
1.
b10001 >

#12750
0!
0.

#12800
1!
1.
b10010 >

#12850
0!
0.

#12900
1!
1.
b10011 >

#12950
0!
0.

#13000
1!
1.
b10100 >

#13050
0!
0.

#13100
1!
1.
b10101 >

#13150
0!
0.

#13200
1!
1.
b10110 >

#13250
0!
0.

#13300
1!
1.
b10111 >

#13350
0!
0.

#13400
1!
1.
b11000 >

#13450
0!
0.

#13500
1!
1.
b11001 >

#13550
0!
0.

#13600
1!
1.
b11010 >

#13650
0!
0.

#13700
1!
1.
b11011 >

#13750
0!
0.

#13800
1!
1.
b11100 >

#13850
0!
0.

#13900
1!
1.
b11101 >

#13950
0!
0.

#14000
1!
1.
b11110 >

#14050
0!
0.

#14100
1!
1.
b11111 >

#14150
0!
0.

#14200
1!
1.
b100000 >

#14250
0!
0.

#14300
1!
1.
b100001 >

#14350
0!
0.

#14400
1!
1.
b100010 >

#14450
0!
0.

#14500
1!
1.
b100011 >

#14550
0!
0.

#14600
1!
1.
b100100 >

#14650
0!
0.

#14700
1!
1.
b100101 >

#14750
0!
0.

#14800
1!
1.
b100110 >

#14850
0!
0.

#14900
1!
1.
b100111 >

#14950
0!
0.

#15000
1!
1.
b101000 >

#15050
0!
0.

#15100
1!
1.
b101001 >

#15150
0!
0.

#15200
1!
1.
b101010 >

#15250
0!
0.

#15300
1!
1.
b101011 >

#15350
0!
0.

#15400
1!
1.
b101100 >

#15450
0!
0.

#15500
1!
1.
b101101 >

#15550
0!
0.

#15600
1!
1.
b101110 >

#15650
0!
0.

#15700
1!
1.
b101111 >

#15750
0!
0.

#15800
1!
1.
b110000 >

#15850
0!
0.

#15900
1!
1.
b110001 >

#15950
0!
0.

#16000
1!
b101011110101111010111001 *
1.
b101011110101111010111001 <
b110010 >

#16050
0!
0.

#16100
1!
b101011110101111010111001 $
1%
1.
b101011110101111010111001 1
12
b10 9

#16150
0!
0.

#16200
1!
1.
b10 8
b100 9

#16250
0!
0.

#16300
1!
1'
1(
1.
14
b101011110101111010111001 6
b100 8

#16350
0!
0.

#16400
1!
0'
0(
b1111111100000001 +
1.
04
b10101111010111101011100 6
b1 7
b0 =

#16450
0!
0.

#16500
1!
1.
b1010111101011110101110 6
b10 7
b1 =

#16550
0!
0.

#16600
1!
1(
1.
b101011110101111010111 6
b11 7
b10 =

#16650
0!
0.

#16700
1!
b1111111100001001 +
1.
b10101111010111101011 6
b100 7
b11 =

#16750
0!
0.

#16800
1!
b1111111100011001 +
1.
b1010111101011110101 6
b101 7
b100 =

#16850
0!
0.

#16900
1!
0(
b1111111100111001 +
1.
b101011110101111010 6
b110 7
b101 =

#16950
0!
0.

#17000
1!
1(
1.
b10101111010111101 6
b111 7
b110 =

#17050
0!
0.

#17100
1!
0(
b1111111110111001 +
1.
b1010111101011110 6
b1000 7
b111 =

#17150
0!
0.

#17200
1!
1(
b1111111010111001 +
1.
b101011110101111 6
b1001 7
b1000 =

#17250
0!
0.

#17300
1!
1.
b10101111010111 6
b1010 7
b1001 =

#17350
0!
0.

#17400
1!
1.
b1010111101011 6
b1011 7
b1010 =

#17450
0!
0.

#17500
1!
1.
b101011110101 6
b1100 7
b1011 =

#17550
0!
0.

#17600
1!
0(
1.
b10101111010 6
b1101 7
b1100 =

#17650
0!
0.

#17700
1!
1(
b1101111010111001 +
1.
b1010111101 6
b1110 7
b1101 =

#17750
0!
0.

#17800
1!
0(
1.
b101011110 6
b1111 7
b1110 =

#17850
0!
0.

#17900
1!
1(
b101111010111001 +
1.
b10101111 6
b10000 7
b1111 =

#17950
0!
0.

#18000
1!
b10101111010111001 +
1.
b1010111 6
b10001 7
b10000 =

#18050
0!
0.

#18100
1!
b110101111010111001 +
1.
b101011 6
b10010 7
b10001 =

#18150
0!
0.

#18200
1!
b1110101111010111001 +
1.
b10101 6
b10011 7
b10010 =

#18250
0!
0.

#18300
1!
0(
b11110101111010111001 +
1.
b1010 6
b10100 7
b10011 =

#18350
0!
0.

#18400
1!
1(
1.
b101 6
b10101 7
b10100 =

#18450
0!
0.

#18500
1!
0(
b1011110101111010111001 +
1.
b10 6
b10110 7
b10101 =

#18550
0!
0.

#18600
1!
1(
1.
b1 6
b10111 7
b1000 9
b10110 =

#18650
0!
0.

#18700
1!
b101011110101111010111001 +
1.
b0 7
b1000 8
b10111 =

#18750
0!
0.

#18800
1!
0%
1.
02
b11000 =

#18850
0!
0.

#18900
1!
1&
1.
13
b1 9
b101011110101111010111001 :
b101011110101111010111001 ;

#18950
0!
0.

#19000
1!
0&
1.
03
b1 8
b1 9
b0 >

#19050
0!
0.

#19100
1!
0(
1.
b0 6
b1 >

#19150
0!
0.

#19200
1!
1.
b10 >

#19250
0!
0.

#19300
1!
1.
b11 >

#19350
0!
0.

#19400
1!
1.
b100 >

#19450
0!
0.

#19500
1!
1.
b101 >

#19550
0!
0.

#19600
1!
1.
b110 >

#19650
0!
0.

#19700
1!
1.
b111 >

#19750
0!
0.

#19800
1!
1.
b1000 >

#19850
0!
0.

#19900
1!
1.
b1001 >

#19950
0!
0.

#20000
1!
1.
b1010 >

#20050
0!
0.

#20100
1!
1.
b1011 >

#20150
0!
0.

#20200
1!
1.
b1100 >

#20250
0!
0.

#20300
1!
1.
b1101 >

#20350
0!
0.

#20400
1!
1.
b1110 >

#20450
0!
0.

#20500
1!
1.
b1111 >

#20550
0!
0.

#20600
1!
1.
b10000 >

#20650
0!
0.

#20700
1!
1.
b10001 >

#20750
0!
0.

#20800
1!
1.
b10010 >

#20850
0!
0.

#20900
1!
1.
b10011 >

#20950
0!
0.

#21000
1!
1.
b10100 >

#21050
0!
0.

#21100
1!
1.
b10101 >

#21150
0!
0.

#21200
1!
1.
b10110 >

#21250
0!
0.

#21300
1!
1.
b10111 >

#21350
0!
0.

#21400
1!
1.
b11000 >

#21450
0!
0.

#21500
1!
1.
b11001 >

#21550
0!
0.

#21600
1!
1.
b11010 >

#21650
0!
0.

#21700
1!
1.
b11011 >

#21750
0!
0.

#21800
1!
1.
b11100 >

#21850
0!
0.

#21900
1!
1.
b11101 >

#21950
0!
0.

#22000
1!
1.
b11110 >

#22050
0!
0.

#22100
1!
1.
b11111 >

#22150
0!
0.

#22200
1!
1.
b100000 >

#22250
0!
0.

#22300
1!
1.
b100001 >

#22350
0!
0.

#22400
1!
1.
b100010 >

#22450
0!
0.

#22500
1!
1.
b100011 >

#22550
0!
0.

#22600
1!
1.
b100100 >

#22650
0!
0.

#22700
1!
1.
b100101 >

#22750
0!
0.

#22800
1!
1.
b100110 >

#22850
0!
0.

#22900
1!
1.
b100111 >

#22950
0!
0.

#23000
1!
1.
b101000 >

#23050
0!
0.

#23100
1!
1.
b101001 >

#23150
0!
0.

#23200
1!
1.
b101010 >

#23250
0!
0.

#23300
1!
1.
b101011 >

#23350
0!
0.

#23400
1!
1.
b101100 >

#23450
0!
0.

#23500
1!
1.
b101101 >

#23550
0!
0.

#23600
1!
1.
b101110 >

#23650
0!
0.

#23700
1!
1.
b101111 >

#23750
0!
0.

#23800
1!
1.
b110000 >

#23850
0!
0.

#23900
1!
1.
b110001 >

#23950
0!
0.

#24000
1!
b100001000000011000000100 *
1.
b100001000000011000000100 <
b110010 >

#24050
0!
0.

#24100
1!
b100001000000011000000100 $
1%
1.
b100001000000011000000100 1
12
b10 9

#24150
0!
0.

#24200
1!
1.
b10 8
b100 9

#24250
0!
0.

#24300
1!
1'
1.
14
b100001000000011000000100 6
b100 8

#24350
0!
0.

#24400
1!
0'
b101011110101111010111000 +
1.
04
b10000100000001100000010 6
b1 7
b0 =

#24450
0!
0.

#24500
1!
1(
1.
b1000010000000110000001 6
b10 7
b1 =

#24550
0!
0.

#24600
1!
0(
b101011110101111010111100 +
1.
b100001000000011000000 6
b11 7
b10 =

#24650
0!
0.

#24700
1!
b101011110101111010110100 +
1.
b10000100000001100000 6
b100 7
b11 =

#24750
0!
0.

#24800
1!
b101011110101111010100100 +
1.
b1000010000000110000 6
b101 7
b100 =

#24850
0!
0.

#24900
1!
b101011110101111010000100 +
1.
b100001000000011000 6
b110 7
b101 =

#24950
0!
0.

#25000
1!
1.
b10000100000001100 6
b111 7
b110 =

#25050
0!
0.

#25100
1!
b101011110101111000000100 +
1.
b1000010000000110 6
b1000 7
b111 =

#25150
0!
0.

#25200
1!
1(
1.
b100001000000011 6
b1001 7
b1000 =

#25250
0!
0.

#25300
1!
1.
b10000100000001 6
b1010 7
b1001 =

#25350
0!
0.

#25400
1!
0(
1.
b1000010000000 6
b1011 7
b1010 =

#25450
0!
0.

#25500
1!
b101011110101011000000100 +
1.
b100001000000 6
b1100 7
b1011 =

#25550
0!
0.

#25600
1!
b101011110100011000000100 +
1.
b10000100000 6
b1101 7
b1100 =

#25650
0!
0.

#25700
1!
1.
b1000010000 6
b1110 7
b1101 =

#25750
0!
0.

#25800
1!
b101011110000011000000100 +
1.
b100001000 6
b1111 7
b1110 =

#25850
0!
0.

#25900
1!
1.
b10000100 6
b10000 7
b1111 =

#25950
0!
0.

#26000
1!
b101011100000011000000100 +
1.
b1000010 6
b10001 7
b10000 =

#26050
0!
0.

#26100
1!
1(
b101011000000011000000100 +
1.
b100001 6
b10010 7
b10001 =

#26150
0!
0.

#26200
1!
0(
1.
b10000 6
b10011 7
b10010 =

#26250
0!
0.

#26300
1!
b101001000000011000000100 +
1.
b1000 6
b10100 7
b10011 =

#26350
0!
0.

#26400
1!
1.
b100 6
b10101 7
b10100 =

#26450
0!
0.

#26500
1!
b100001000000011000000100 +
1.
b10 6
b10110 7
b10101 =

#26550
0!
0.

#26600
1!
1(
1.
b1 6
b10111 7
b1000 9
b10110 =

#26650
0!
0.

#26700
1!
1.
b0 7
b1000 8
b10111 =

#26750
0!
0.

#26800
1!
0%
1.
02
b11000 =

#26850
0!
0.

#26900
1!
1&
1.
13
b1 9
b100001000000011000000100 :
b100001000000011000000100 ;

#26950
0!
0.

#27000
1!
0&
1.
03
b1 8
b1 9
b0 >

#27050
0!
0.

#27100
1!
0(
1.
b0 6
b1 >

#27150
0!
0.

#27200
1!
1.
b10 >

#27250
0!
0.

#27300
1!
1.
b11 >

#27350
0!
0.

#27400
1!
1.
b100 >

#27450
0!
0.

#27500
1!
1.
b101 >

#27550
0!
0.

#27600
1!
1.
b110 >

#27650
0!
0.

#27700
1!
1.
b111 >

#27750
0!
0.

#27800
1!
1.
b1000 >

#27850
0!
0.

#27900
1!
1.
b1001 >

#27950
0!
0.

#28000
1!
1.
b1010 >

#28050
0!
0.

#28100
1!
1.
b1011 >

#28150
0!
0.

#28200
1!
1.
b1100 >

#28250
0!
0.

#28300
1!
1.
b1101 >

#28350
0!
0.

#28400
1!
1.
b1110 >

#28450
0!
0.

#28500
1!
1.
b1111 >

#28550
0!
0.

#28600
1!
1.
b10000 >

#28650
0!
0.

#28700
1!
1.
b10001 >

#28750
0!
0.

#28800
1!
1.
b10010 >

#28850
0!
0.

#28900
1!
1.
b10011 >

#28950
0!
0.

#29000
1!
1.
b10100 >

#29050
0!
0.

#29100
1!
1.
b10101 >

#29150
0!
0.

#29200
1!
1.
b10110 >

#29250
0!
0.

#29300
1!
1.
b10111 >

#29350
0!
0.

#29400
1!
1.
b11000 >

#29450
0!
0.

#29500
1!
1.
b11001 >

#29550
0!
0.

#29600
1!
1.
b11010 >

#29650
0!
0.

#29700
1!
1.
b11011 >

#29750
0!
0.

#29800
1!
1.
b11100 >

#29850
0!
0.

#29900
1!
1.
b11101 >

#29950
0!
0.

#30000
1!
1.
b11110 >

#30050
0!
0.

#30100
1!
1.
b11111 >

#30150
0!
0.

#30200
1!
1.
b100000 >

#30250
0!
0.

#30300
1!
1.
b100001 >

#30350
0!
0.

#30400
1!
1.
b100010 >

#30450
0!
0.

#30500
1!
1.
b100011 >

#30550
0!
0.

#30600
1!
1.
b100100 >

#30650
0!
0.

#30700
1!
1.
b100101 >

#30750
0!
0.

#30800
1!
1.
b100110 >

#30850
0!
0.

#30900
1!
1.
b100111 >

#30950
0!
0.

#31000
1!
1.
b101000 >

#31050
0!
0.

#31100
1!
1.
b101001 >

#31150
0!
0.

#31200
1!
1.
b101010 >

#31250
0!
0.

#31300
1!
1.
b101011 >

#31350
0!
0.

#31400
1!
1.
b101100 >

#31450
0!
0.

#31500
1!
1.
b101101 >

#31550
0!
0.

#31600
1!
1.
b101110 >

#31650
0!
0.

#31700
1!
1.
b101111 >

#31750
0!
0.

#31800
1!
1.
b110000 >

#31850
0!
0.

#31900
1!
1.
b110001 >

#31950
0!
0.

#32000
1!
b111111101100111001111010 *
1.
b111111101100111001111010 <
b110010 >

#32050
0!
0.

#32100
1!
b111111101100111001111010 $
1%
1.
b111111101100111001111010 1
12
b10 9

#32150
0!
0.

#32200
1!
1.
b10 8
b100 9

#32250
0!
0.

#32300
1!
1'
1.
14
b111111101100111001111010 6
b100 8

#32350
0!
0.

#32400
1!
0'
1(
1.
04
b11111110110011100111101 6
b1 7
b0 =

#32450
0!
0.

#32500
1!
0(
b100001000000011000000110 +
1.
b1111111011001110011110 6
b10 7
b1 =

#32550
0!
0.

#32600
1!
1(
b100001000000011000000010 +
1.
b111111101100111001111 6
b11 7
b10 =

#32650
0!
0.

#32700
1!
b100001000000011000001010 +
1.
b11111110110011100111 6
b100 7
b11 =

#32750
0!
0.

#32800
1!
b100001000000011000011010 +
1.
b1111111011001110011 6
b101 7
b100 =

#32850
0!
0.

#32900
1!
b100001000000011000111010 +
1.
b111111101100111001 6
b110 7
b101 =

#32950
0!
0.

#33000
1!
0(
b100001000000011001111010 +
1.
b11111110110011100 6
b111 7
b110 =

#33050
0!
0.

#33100
1!
1.
b1111111011001110 6
b1000 7
b111 =

#33150
0!
0.

#33200
1!
1(
1.
b111111101100111 6
b1001 7
b1000 =

#33250
0!
0.

#33300
1!
1.
b11111110110011 6
b1010 7
b1001 =

#33350
0!
0.

