hdl/verilog/shift_reg/src/shift_reg.v
module shift_reg
#(parameter LENGTH = 8)
    (
        input i_clk,
        input i_rst,
        input i_din,
        output o_dout
    );

    reg [LENGTH-1:0] shift_reg;
    assign o_dout = shift_reg[LENGTH-1];

    always @(posedge i_clk) begin
        if (i_rst) begin
            shift_reg = { (LENGTH-1){1'b0} };
        end else begin
            shift_reg = { shift_reg[LENGTH-2:0], i_din };
        end
    end

endmodule

hdl/verilog/shift_reg/src/top_level.v
module top_level
#(parameter LENGTH = 32)
    (
        input wire i_clk,
        input wire i_rst,
        input wire i_din,
        output wire o_dout
    );

    shift_reg #(.LENGTH(LENGTH)) shift_reg_0 (
        .i_clk(i_clk),
        .i_rst(i_rst),
        .i_din(i_din),
        .o_dout(o_dout)
    );

endmodule

hdl/verilog/shift_reg/verif/tb_shift_reg.sv

module tb_shift_reg;

    localparam LENGTH = 8;
    int num_errors = 0;
    reg tb_clk;
    reg tb_rst;
    reg tb_din;
    reg [LENGTH-1:0] tb_word;
    wire tb_dout;

    // instantiation unit under test 
    top_level #(.LENGTH(LENGTH)) dut (
        .i_clk(tb_clk),
        .i_rst(tb_rst),
        .i_din(tb_din),
        .o_dout(tb_dout)
    );

    always #5 tb_clk = ~tb_clk;

    initial begin
        $dumpfile("waveform.vcd");
        $dumpvars;

        num_errors = 0;
        tb_clk = 1;
        tb_rst = 1;
        tb_word = $urandom();
        #10;

        tb_rst = 0;
        for (int i = 0; i < LENGTH; i++) begin
            tb_din = tb_word[i];
            #10;
        end

        $finish;
    end // initial
endmodule

hdl/verilog/shift_reg/sim_functional/waveform.vcd
$date
   Thu Oct 24 16:17:46 2024
$end

$version
  2023.2.2
  $dumpfile ("waveform.vcd") 
$end

$timescale
  1ps
$end

$scope module tb_shift_reg $end
$var reg 32 ! num_errors [31:0] $end
$var reg 1 " tb_clk $end
$var reg 1 # tb_rst $end
$var reg 1 $ tb_din $end
$var reg 32 % tb_word [31:0] $end
$var wire 1 & tb_dout $end
$scope module dut $end
$var wire 1 ' i_clk $end
$var wire 1 ( i_rst $end
$var wire 1 ) i_din $end
$var wire 1 & o_dout $end
$scope module shift_reg_0 $end
$var wire 1 ' i_clk $end
$var wire 1 ( i_rst $end
$var wire 1 ) i_din $end
$var wire 1 & o_dout $end
$var reg 32 * shift_reg [31:0] $end
$upscope $end
$upscope $end
$scope begin Block33_3 $end
$var reg 32 + i [31:0] $end
$upscope $end
$upscope $end
$enddefinitions $end

#0
$dumpvars
b0 !
1"
1#
x$
b1100100110010010011000111011011 %
0&
1'
1(
x)
b0 *
b0 +
$end

#5000
0"
0'

#10000
1"
0#
1$
1'
0(
1)
b1 *

#15000
0"
0'

#20000
1"
1'
b11 *
b1 +

#25000
0"
0'

#30000
1"
0$
1'
0)
b110 *
b10 +

#35000
0"
0'

#40000
1"
1$
1'
1)
b1101 *
b11 +

#45000
0"
0'

#50000
1"
1'
b11011 *
b100 +

#55000
0"
0'

#60000
1"
0$
1'
0)
b110110 *
b101 +

#65000
0"
0'

#70000
1"
1$
1'
1)
b1101101 *
b110 +

#75000
0"
0'

#80000
1"
1'
b11011011 *
b111 +

#85000
0"
0'

#90000
1"
1'
b110110111 *
b1000 +

#95000
0"
0'

#100000
1"
0$
1'
0)
b1101101110 *
b1001 +

#105000
0"
0'

#110000
1"
1'
b11011011100 *
b1010 +

#115000
0"
0'

#120000
1"
1'
b110110111000 *
b1011 +

#125000
0"
0'

#130000
1"
1$
1'
1)
b1101101110001 *
b1100 +

#135000
0"
0'

#140000
1"
1'
b11011011100011 *
b1101 +

#145000
0"
0'

#150000
1"
0$
1'
0)
b110110111000110 *
b1110 +

#155000
0"
0'

#160000
1"
1'
b1101101110001100 *
b1111 +

#165000
0"
0'

#170000
1"
1$
1'
1)
b11011011100011001 *
b10000 +

#175000
0"
0'

#180000
1"
0$
1'
0)
b110110111000110010 *
b10001 +

#185000
0"
0'

#190000
1"
1'
b1101101110001100100 *
b10010 +

#195000
0"
0'

#200000
1"
1$
1'
1)
b11011011100011001001 *
b10011 +

#205000
0"
0'

#210000
1"
0$
1'
0)
b110110111000110010010 *
b10100 +

#215000
0"
0'

#220000
1"
1'
b1101101110001100100100 *
b10101 +

#225000
0"
0'

#230000
1"
1$
1'
1)
b11011011100011001001001 *
b10110 +

#235000
0"
0'

#240000
1"
1'
b110110111000110010010011 *
b10111 +

#245000
0"
0'

#250000
1"
0$
1'
0)
b1101101110001100100100110 *
b11000 +

#255000
0"
0'

#260000
1"
1'
b11011011100011001001001100 *
b11001 +

#265000
0"
0'

#270000
1"
1$
1'
1)
b110110111000110010010011001 *
b11010 +

#275000
0"
0'

#280000
1"
0$
1'
0)
b1101101110001100100100110010 *
b11011 +

#285000
0"
0'

#290000
1"
1'
b11011011100011001001001100100 *
b11100 +

#295000
0"
0'

#300000
1"
1$
1'
1)
b110110111000110010010011001001 *
b11101 +

#305000
0"
0'

#310000
1"
1'
b1101101110001100100100110010011 *
b11110 +

#315000
0"
0'

#320000
1"
0$
1&
1'
0)
b11011011100011001001001100100110 *
b11111 +

#325000
0"
0'

#330000
1"
x$
1'
x)
b1011011100011001001001100100110x *
b100000 +

#335000
0"
0'

#340000
1"
0&
1'
b11011100011001001001100100110xx *
b100001 +

#345000
0"
0'

#350000
1"
1&
1'
b11011100011001001001100100110xxx *
b100010 +

#355000
0"
0'

#360000
1"
1'
b1011100011001001001100100110xxxx *
b100011 +

#365000
0"
0'

#370000
1"
0&
1'
b11100011001001001100100110xxxxx *
b100100 +

#375000
0"
0'

#380000
1"
1&
1'
b11100011001001001100100110xxxxxx *
b100101 +

#385000
0"
0'

#390000
1"
1'
b1100011001001001100100110xxxxxxx *
b100110 +

#395000
0"
0'

#400000
1"
1'
b100011001001001100100110xxxxxxxx *
b100111 +

#405000
0"
0'

#410000
1"
0&
1'
b11001001001100100110xxxxxxxxx *
b101000 +

#415000
0"
0'

#420000
1"
1'
b11001001001100100110xxxxxxxxxx *
b101001 +

#425000
0"
0'

#430000
1"
1'
b11001001001100100110xxxxxxxxxxx *
b101010 +

#435000
0"
0'

#440000
1"
1&
1'
b11001001001100100110xxxxxxxxxxxx *
b101011 +

#445000
0"
0'

#450000
1"
1'
b1001001001100100110xxxxxxxxxxxxx *
b101100 +

#455000
0"
0'

#460000
1"
0&
1'
b1001001100100110xxxxxxxxxxxxxx *
b101101 +

#465000
0"
0'

#470000
1"
1'
b1001001100100110xxxxxxxxxxxxxxx *
b101110 +

#475000
0"
0'

#480000
1"
1&
1'
b1001001100100110xxxxxxxxxxxxxxxx *
b101111 +

#485000
0"
0'

#490000
1"
0&
1'
b1001100100110xxxxxxxxxxxxxxxxx *
b110000 +

#495000
0"
0'

#500000
1"
1'
b1001100100110xxxxxxxxxxxxxxxxxx *
b110001 +

#505000
0"
0'

#510000
1"
1&
1'
b1001100100110xxxxxxxxxxxxxxxxxxx *
b110010 +

#515000
0"
0'

#520000
1"
0&
1'
b1100100110xxxxxxxxxxxxxxxxxxxx *
b110011 +

#525000
0"
0'

#530000
1"
1'
b1100100110xxxxxxxxxxxxxxxxxxxxx *
b110100 +

#535000
0"
0'

#540000
1"
1&
1'
b1100100110xxxxxxxxxxxxxxxxxxxxxx *
b110101 +

#545000
0"
0'

#550000
1"
1'
b100100110xxxxxxxxxxxxxxxxxxxxxxx *
b110110 +

#555000
0"
0'

#560000
1"
0&
1'
b100110xxxxxxxxxxxxxxxxxxxxxxxx *
b110111 +

#565000
0"
0'

#570000
1"
1'
b100110xxxxxxxxxxxxxxxxxxxxxxxxx *
b111000 +

#575000
0"
0'

#580000
1"
1&
1'
b100110xxxxxxxxxxxxxxxxxxxxxxxxxx *
b111001 +

#585000
0"
0'

#590000
1"
0&
1'
b110xxxxxxxxxxxxxxxxxxxxxxxxxxx *
b111010 +

#595000
0"
0'

#600000
1"
1'
b110xxxxxxxxxxxxxxxxxxxxxxxxxxxx *
b111011 +

#605000
0"
0'

#610000
1"
1&
1'
b110xxxxxxxxxxxxxxxxxxxxxxxxxxxxx *
b111100 +

#615000
0"
0'

#620000
1"
1'
b10xxxxxxxxxxxxxxxxxxxxxxxxxxxxxx *
b111101 +

#625000
0"
0'

#630000
1"
0&
1'
b0xxxxxxxxxxxxxxxxxxxxxxxxxxxxxxx *
b111110 +

#635000
0"
0'

#640000
1"
x&
1'
bx *
b111111 +

#645000
0"
0'

#650000
1"
1'
b1000000 +

#655000
0"
0'

#660000
1"
1'
b1000001 +

#665000
0"
0'

#670000
1"
1'
b1000010 +

#675000
0"
0'

#680000
1"
1'
b1000011 +

#685000
0"
0'

#690000
1"
1'
b1000100 +

#695000
0"
0'

#700000
1"
1'
b1000101 +

#705000
0"
0'

#710000
1"
1'
b1000110 +

#715000
0"
0'

#720000
1"
1'
b1000111 +

#725000
0"
0'

#730000
1"
1'
b1001000 +

#735000
0"
0'

#740000
1"
1'
b1001001 +

#745000
0"
0'

#750000
1"
1'
b1001010 +

#755000
0"
0'

#760000
1"
1'
b1001011 +

#765000
0"
0'

#770000
1"
1'
b1001100 +

#775000
0"
0'

#780000
1"
1'
b1001101 +

#785000
0"
0'

#790000
1"
1'
b1001110 +

#795000
0"
0'

#800000
1"
1'
b1001111 +

#805000
0"
0'

#810000
1"
1'
b1010000 +

#815000
0"
0'

#820000
1"
1'
b1010001 +

#825000
0"
0'

#830000
1"
1'
b1010010 +

#835000
0"
0'

#840000
1"
1'
b1010011 +

#845000
0"
0'

#850000
1"
1'
b1010100 +

#855000
0"
0'

#860000
1"
1'
b1010101 +

#865000
0"
0'

#870000
1"
1'
b1010110 +

#875000
0"
0'

#880000
1"
1'
b1010111 +

#885000
0"
0'

#890000
1"
1'
b1011000 +

#895000
0"
0'

#900000
1"
1'
b1011001 +

#905000
0"
0'

#910000
1"
1'
b1011010 +

#915000
0"
0'

#920000
1"
1'
b1011011 +

#925000
0"
0'

#930000
1"
1'
b1011100 +

#935000
0"
0'

#940000
1"
1'
b1011101 +

#945000
0"
0'

#950000
1"
1'
b1011110 +

#955000
0"
0'

#960000
1"
1'
b1011111 +

#965000
0"
0'

#970000
1"
1'
b1100000 +

#975000
0"
0'

#980000
1"
1'
b1100001 +

#985000
0"
0'

#990000
1"
1'
b1100010 +

#995000
0"
0'

#1000000
1"
1'
b1100011 +

#1005000
0"
0'

#1010000
b1100100 +
